Workbook

Sheet Sheet1
A1: sku | B1: qty_available | C1: min_order_qty | D1: name | E1: upc | F1: product_id | G1: image_url | H1: material | I1: dimensions | J1: color | K1: min_case_price | L1: min_case_qty | M1: case_price | N1: case_qty | O1: bullet_1 | P1: bullet_2 | Q1: bullet_3 | R1: bullet_4 | S1: bullet_5 | T1: bullet_6 | U1: bullet_7 | V1: bullet_8 | W1: bullet_9 | X1: bullet_10 | Y1: bullet_11 | Z1: bullet_12 | AA1: bullet_13 | AB1: bullet_14 | AC1: bullet_15 | AD1: bullet_16
A2: G3216179 | B2: 2232 | C2: 6 | D2: 4' Red Ball Garland | E2: 048893851880 | F2: 109721 | G2: https://www.razimports.com/media/catalog_product/ImagesFiles2/G3216179.jpg?quality=100&bg-color=255,255,255&fit=bounds&height=1000&width=1000&canvas=1000:1000 | H2: Made of PLASTIC | I2: Measures: 4' L | J2: RED | K2: 14.25 | L2: (6EA) Min. | M2: 12.60 | N2: (12EA) Case
A3: 3911406 | B3: 2082 | C3: 2 | D3: 24" Church Lighted Print | E3: 048893073978 | F3: 92654 | G3: https://www.razimports.com/media/catalog_product/ImagesFiles2/3911406.jpg?quality=100&bg-color=255,255,255&fit=bounds&height=1000&width=1000&canvas=1000:1000 | H3: Made of POLYESTER CANVAS | I3: Measures: 24" L x 1" W x 18" H | J3: MULTICOLOR | K3: 31.40 | L3: (2EA) Min. | M3: 27.70 | N3: (8EA) Case | O3: REQUIRES 3 AA BATTERIES | P3: 6 HOUR TIMER REPEATS EVERY 18 HOURS | Q3: CORNER BUTTON ACTIVATED | R3: Artist: © Galaxy of Graphics Licensing LLC, Sall
A4: G3416336 | B4: 1920 | C4: 6 | D4: 4' Multicolor Ball Garland | E4: 048893987831 | F4: 109724 | G4: https://www.razimports.com/media/catalog_product/ImagesFiles2/G3416336.jpg?quality=100&bg-color=255,255,255&fit=bounds&height=1000&width=1000&canvas=1000:1000 | H4: Made of PLASTIC | I4: Measures: 4' L | J4: MULTICOLOR | K4: 14.90 | L4: (6EA) Min. | M4: 13.20 | N4: (12EA) Case
A5: 4559488 | B5: 1592 | C5: 8 | D5: 10.5" Gold Tree Taper Candles | E5: 048893931223 | F5: 104945 | G5: https://www.razimports.com/media/catalog_product/ImagesFiles2/4559488.jpg?quality=100&bg-color=255,255,255&fit=bounds&height=1000&width=1000&canvas=1000:1000 | H5: Made of WAX | I5: Measures: 1.75"D x 10.5"H | J5: SET OF 2 GOLD - YELLOW | K5: 16.00 | L5: (8SET) Min. | M5: 14.40 | N5: (16SET) Case | O5: REQUIRES 2 AAA BATTERIES EACH | P5: 6 HOUR TIMER REPEATS EVERY 18 HOURS | Q5: BATTERY LIFE APPROX 120 HOURS
A6: 4533532 | B6: 1536 | C6: 24 | D6: 4" Clear Seamless Iridescent Ball | E6: 048893931292 | F6: 102740 | G6: https://www.razimports.com/media/catalog_product/ImagesFiles2/4533532.jpg?quality=100&bg-color=255,255,255&fit=bounds&height=1000&width=1000&canvas=1000:1000 | H6: Made of PET (POLYETHYLENE TEREPHTHALATE) | I6: Measures: 4" D | J6: CLEAR | K6: 2.75 | L6: (24EA) Min. | M6: 2.45 | N6: (48EA) Case
A7: 4124532 | B7: 1212 | C7: 24 | D7: *SB* 5" Local Grown Christmas Trees Ball Ornament | E7: 048893212469 | F7: 93086 | G7: https://www.razimports.com/media/catalog_product/ImagesFiles2/4124532.jpg?quality=100&bg-color=255,255,255&fit=bounds&height=1000&width=1000&canvas=1000:1000 | H7: Made of GLASS | I7: Measures: 5" D | J7: WHITE | K7: 7.00 | L7: (6EA) Minimum | M7: 3.60 | N7: (24EA) | O7: Artist: © Nicole Tamarin
A8: 4432922 | B8: 1200 | C8: 8 | D8: 10.5" Ivory Tree Taper Candles | E8: 048893490805 | F8: 96116 | G8: https://www.razimports.com/media/catalog_product/ImagesFiles2/4432922.jpg?quality=100&bg-color=255,255,255&fit=bounds&height=1000&width=1000&canvas=1000:1000 | H8: Made of WAX | I8: Measures: 1.75"D x 10.5"H | J8: SET OF 2 WHITE - IVORY | K8: 15.45 | L8: (8SET) Min. | M8: 13.85 | N8: (16SET) Case | O8: REQUIRES 2 AAA BATTERIES EACH | P8: 6 HOUR TIMER REPEATS EVERY 18 HOURS | Q8: INDOOR USE ONLY | R8: LIGHTS APPROX 20,000 HOURS
A9: 4324035 | B9: 1180 | C9: 10 | D9: 6" Clip-On Lighted Candles with Remote | E9: 048893546533 | F9: 94448 | G9: https://www.razimports.com/media/catalog_product/ImagesFiles2/4324035.jpg?quality=100&bg-color=255,255,255&fit=bounds&height=1000&width=1000&canvas=1000:1000 | H9: Made of PLASTIC | I9: Measures: 1.5"L x 0.5"W x 7"H | J9: BOX OF 10 WHITE | K9: 20.75 | L9: (10BOX) Min. | M9: 18.55 | N9: (20BOX) Case | O9: EACH CANDLE REQUIRES 1 AAA BATTERY | P9: 6 HOUR TIMER REPEATS EVERY 18 HOURS | Q9: INCLUDES REMOTE WITH CR2025 BATTERY | R9: INDOOR USE ONLY | S9: LIGHTS APPROX 12,000 HOURS
A10: F4517615 | B10: 1140 | C10: 12 | D10: 32" Pearl and Crystal Dripping Spray | E10: 048893937966 | F10: 108620 | G10: https://www.razimports.com/media/catalog_product/ImagesFiles2/F4517615.jpg?quality=100&bg-color=255,255,255&fit=bounds&height=1000&width=1000&canvas=1000:1000 | H10: Made of PLASTIC | I10: Measures: 32" L | J10: GOLD | K10: 8.70 | L10: (12EA) Min. | M10: 7.25 | N10: (36EA) Case
A11: G4516359 | B11: 1104 | C11: 12 | D11: 6' Pearl Garland | E11: 048893425883 | F11: 110099 | G11: https://www.razimports.com/media/catalog_product/ImagesFiles2/G4516359.jpg?quality=100&bg-color=255,255,255&fit=bounds&height=1000&width=1000&canvas=1000:1000 | H11: Made of PLASTIC | I11: Measures: 6' L | J11: WHITE - PEARL | K11: 10.35 | L11: (12EA) Min. | M11: 8.95 | N11: (24EA) Case
A12: G4416416 | B12: 1080 | C12: 12 | D12: 15' x 0.5" Red Beaded Garland | E12: 048893986865 | F12: 109952 | G12: https://www.razimports.com/media/catalog_product/ImagesFiles2/G4416416.jpg?quality=100&bg-color=255,255,255&fit=bounds&height=1000&width=1000&canvas=1000:1000 | H12: Made of PLASTIC | I12: Measures: 15' L | J12: RED | K12: 6.30 | L12: (12EA) Min. | M12: 5.30 | N12: (48EA) Case | O12: 0.5" GIRTH | P12: Catalog (Christmas 2025) on page 27
A13: G4516540 | B13: 1056 | C13: 12 | D13: 15' X 0.5" Blue Beaded Garland | E13: 048893425814 | F13: 110114 | G13: https://www.razimports.com/media/catalog_product/ImagesFiles2/G4516540.jpg?quality=100&bg-color=255,255,255&fit=bounds&height=1000&width=1000&canvas=1000:1000 | H13: Made of PLASTIC | I13: Measures: 15' L | J13: BLUE | K13: 6.30 | L13: (12EA) Min. | M13: 5.30 | N13: (48EA) Case | O13: 0.5" GIRTH
A14: G3526011 | B14: 1044 | C14: 12 | D14: 15' x 0.5" Gold Beaded Garland | E14: 048893673635 | F14: 109730 | G14: https://www.razimports.com/media/catalog_product/ImagesFiles2/G3526011.jpg?quality=100&bg-color=255,255,255&fit=bounds&height=1000&width=1000&canvas=1000:1000 | H14: Made of PLASTIC | I14: Measures: 15' L | J14: GOLD - CHAMPAGNE | K14: 6.30 | L14: (12EA) Min. | M14: 5.30 | N14: (48EA) Case | O14: 0.5" GIRTH | P14: Catalog (Christmas 2025) on page 131
A15: 4324047 | B15: 1008 | C15: 12 | D15: *SB* 2" X 4" Red Glass Ivory Pillar Candle | E15: 048893531133 | F15: 94463 | G15: https://www.razimports.com/media/catalog_product/ImagesFiles2/4324047.jpg?quality=100&bg-color=255,255,255&fit=bounds&height=1000&width=1000&canvas=1000:1000 | H15: Made of PLASTIC | I15: Measures: 2" D x 4" H | J15: RED | K15: 5.50 | L15: (12EA) Minimum | M15: 3.00 | N15: (12EA) | O15: REQUIRES 2 AA BATTERIES | P15: 6 HOUR TIMER REPEATS EVERY 18 HOURS | Q15: BATTERY LIFE APPROX 160 HOURS | R15: REMOTE READY | S15: CAN BE USED WITH REMOTE #X4324020
A16: F4542099 | B16: 996 | C16: 12 | D16: 24" Champagne and Pearl Spray | E16: 048893936976 | F16: 109043 | G16: https://www.razimports.com/media/catalog_product/ImagesFiles2/F4542099.jpg?quality=100&bg-color=255,255,255&fit=bounds&height=1000&width=1000&canvas=1000:1000 | H16: Made of PE (POLYETHYLENE) | I16: Measures: 24" L | J16: WHITE - PEARL | K16: 5.65 | L16: (12EA) Min. | M16: 4.75 | N16: (36EA) Case | O16: Catalog (Christmas 2025) on page 293
A17: G4416225 | B17: 936 | C17: 12 | D17: 6' Pearl Garland | E17: 048893986933 | F17: 109940 | G17: https://www.razimports.com/media/catalog_product/ImagesFiles2/G4416225.jpg?quality=100&bg-color=255,255,255&fit=bounds&height=1000&width=1000&canvas=1000:1000 | H17: Made of PLASTIC | I17: Measures: 6' L | J17: IVORY | K17: 9.80 | L17: (12EA) Min. | M17: 8.50 | N17: (24EA) Case | O17: Catalog (Christmas 2025) on page 241
A18: 4432921 | B18: 912 | C18: 8 | D18: 10.5" Green Tree Taper Candles | E18: 048893490812 | F18: 96113 | G18: https://www.razimports.com/media/catalog_product/ImagesFiles2/4432921.jpg?quality=100&bg-color=255,255,255&fit=bounds&height=1000&width=1000&canvas=1000:1000 | H18: Made of WAX | I18: Measures: 1.75"D x 10.5"H | J18: SET OF 2 GREEN | K18: 15.45 | L18: (8SET) Min. | M18: 13.85 | N18: (16SET) Case | O18: REQUIRES 2 AAA BATTERIES EACH | P18: 6 HOUR TIMER REPEATS EVERY 18 HOURS | Q18: INDOOR USE ONLY | R18: LIGHTS APPROX 20,000 HOURS
A19: 4533520 | B19: 864 | C19: 24 | D19: 4" Teal Seamless Iridescent Ball | E19: 048893931421 | F19: 102704 | G19: https://www.razimports.com/media/catalog_product/ImagesFiles2/4533520.jpg?quality=100&bg-color=255,255,255&fit=bounds&height=1000&width=1000&canvas=1000:1000 | H19: Made of PET (POLYETHYLENE TEREPHTHALATE) | I19: Measures: 4" D | J19: BLUE - TEAL | K19: 2.75 | L19: (24EA) Min. | M19: 2.45 | N19: (48EA) Case | O19: Catalog (Christmas 2025) on page 439
A20: F4502264 | B20: 840 | C20: 12 | D20: 27" Holly Berry Felt Spray | E20: 048893939663 | F20: 108128 | G20: https://www.razimports.com/media/catalog_product/ImagesFiles2/F4502264.jpg?quality=100&bg-color=255,255,255&fit=bounds&height=1000&width=1000&canvas=1000:1000 | H20: Made of POLYESTER | I20: Measures: 27" L | J20: GREEN | K20: 8.10 | L20: (12EA) Min. | M20: 7.15 | N20: (24EA) Case
A21: G4517606 | B21: 840 | C21: 12 | D21: 5' Pearl and Crystal Beaded Garland | E21: 048893425678 | F21: 110138 | G21: https://www.razimports.com/media/catalog_product/ImagesFiles2/G4517606.jpg?quality=100&bg-color=255,255,255&fit=bounds&height=1000&width=1000&canvas=1000:1000 | H21: Made of PLASTIC | I21: Measures: 5' L | J21: WHITE - PEARL | K21: 8.30 | L21: (12EA) Min. | M21: 6.90 | N21: (36EA) Case
A22: 37094 | B22: 802 | C22: 8 | D22: *SB* 8" Moving Flame Red Pillar Candles With Remote, Set/3 | E22: 048893921507 | F22: 92468 | G22: https://www.razimports.com/media/catalog_product/ImagesFiles2/37094.jpg?quality=100&bg-color=255,255,255&fit=bounds&height=1000&width=1000&canvas=1000:1000 | H22: Made of WAX | I22: Measures: 3"D x 8"H; 3"D x 6"H; 3"D x 4.5"H | J22: SET OF 4 RED-CINNAMON SCENTED | K22: 64.50 | L22: (8SET) Minimum | M22: 38.70 | N22: (8SET) | O22: REQUIRES 2 C BATTERIES | P22: 5 HOUR TIMER REPEATS EVERY 19 HOURS | Q22: BATTERY LIFE APPROX 500 HOURS | R22: REMOTE READY | S22: CAN BE USED WITH REMOTE #X15997
A23: 4310135 | B23: 768 | C23: 24 | D23: 3.5" Beaded Berry Candle Ring | E23: 048893524845 | F23: 93956 | G23: https://www.razimports.com/media/catalog_product/ImagesFiles2/4310135.jpg?quality=100&bg-color=255,255,255&fit=bounds&height=1000&width=1000&canvas=1000:1000 | H23: Made of GYPSUM | I23: Measures: 3.5" D | J23: MULTICOLOR | K23: 2.65 | L23: (24EA) Min. | M23: 2.25 | N23: (144EA) Case | O23: FITS TAPER CANDLE
A24: 4533526 | B24: 768 | C24: 24 | D24: 4" Purple Seamless Iridescent Ball | E24: 048893931360 | F24: 102722 | G24: https://www.razimports.com/media/catalog_product/ImagesFiles2/4533526.jpg?quality=100&bg-color=255,255,255&fit=bounds&height=1000&width=1000&canvas=1000:1000 | H24: Made of PET (POLYETHYLENE TEREPHTHALATE) | I24: Measures: 4" D | J24: PURPLE | K24: 2.75 | L24: (24EA) Min. | M24: 2.45 | N24: (48EA) Case | O24: Catalog (Christmas 2025) on page 439
A25: 4202410 | B25: 756 | C25: 12 | D25: *SB* 9" Knit Packages with Plaid Bows | E25: 048893809348 | F25: 93317 | G25: https://www.razimports.com/media/catalog_product/ImagesFiles2/4202410.jpg?quality=100&bg-color=255,255,255&fit=bounds&height=1000&width=1000&canvas=1000:1000 | H25: Made of STYROFOAM | I25: Measures: 5.25"L x 5.25"W x 9"H; 5.25"L x 5.25"W x 6"H | J25: SET OF 2 WHITE - CREAM | K25: 17.55 | L25: (3SET) Minimum | M25: 9.15 | N25: (12SET)
A26: G4506740 | B26: 756 | C26: 12 | D26: 4' Wired Vintage Garland | E26: 048893936211 | F26: 110021 | G26: https://www.razimports.com/media/catalog_product/ImagesFiles2/G4506740.jpg?quality=100&bg-color=255,255,255&fit=bounds&height=1000&width=1000&canvas=1000:1000 | H26: Made of PLASTIC | I26: Measures: 4' L | J26: MULTICOLOR | K26: 4.95 | L26: (12EA) Min. | M26: 4.10 | N26: (48EA) Case
A27: R4571854 | B27: 750 | C27: 6 | D27: 1.5" X 10 Yds Green Satin with Red Pom Pom Edge Wired Ribbon | E27: 048893424107 | F27: 110846 | G27: https://www.razimports.com/media/catalog_product/ImagesFiles2/R4571854.jpg?quality=100&bg-color=255,255,255&fit=bounds&height=1000&width=1000&canvas=1000:1000 | H27: Made of POLYESTER | I27: Measures: 10YDS L x 1.5" W | J27: MULTICOLOR | K27: 13.70 | L27: (6EA) Min. | M27: 12.20 | N27: (12EA) Case | O27: Catalog (Christmas 2025) on page 428
A28: F4422726 | B28: 744 | C28: 12 | D28: 24" Glittered Pearl Fern Spray | E28: 048893483883 | F28: 107888 | G28: https://www.razimports.com/media/catalog_product/ImagesFiles2/F4422726.jpg?quality=100&bg-color=255,255,255&fit=bounds&height=1000&width=1000&canvas=1000:1000 | H28: Made of PE (POLYETHYLENE) | I28: Measures: 24" L | J28: NATURAL | K28: 4.80 | L28: (12EA) Min. | M28: 4.00 | N28: (48EA) Case
A29: G4516539 | B29: 744 | C29: 12 | D29: 15' X 0.5" Green Beaded Garland | E29: 048893425838 | F29: 110111 | G29: https://www.razimports.com/media/catalog_product/ImagesFiles2/G4516539.jpg?quality=100&bg-color=255,255,255&fit=bounds&height=1000&width=1000&canvas=1000:1000 | H29: Made of PLASTIC | I29: Measures: 15' L | J29: GREEN | K29: 6.30 | L29: (12EA) Min. | M29: 5.30 | N29: (48EA) Case | O29: 0.5" GIRTH
A30: 4514868 | B30: 720 | C30: 24 | D30: 4" Sprinkled Ball Ornament | E30: 048893955878 | F30: 98855 | G30: https://www.razimports.com/media/catalog_product/ImagesFiles2/4514868.jpg?quality=100&bg-color=255,255,255&fit=bounds&height=1000&width=1000&canvas=1000:1000 | H30: Made of PLASTIC | I30: Measures: 4"D | J30: 3 ASST MULTICOLOR | K30: 3.20 | L30: (24EA) Min. | M30: 2.80 | N30: (48EA) Case
A31: F4206798 | B31: 720 | C31: 48 | D31: *SB* 12" Blue Plaid Poinsettia Stem | E31: 048893974343 | F31: 107639 | G31: https://www.razimports.com/media/catalog_product/ImagesFiles2/F4206798.jpg?quality=100&bg-color=255,255,255&fit=bounds&height=1000&width=1000&canvas=1000:1000 | H31: Made of POLYESTER | I31: Measures: 10" D x 12" H | J31: BLUE - DARK | K31: 6.50 | L31: (12EA) Minimum | M31: 3.40 | N31: (48EA)
A32: 4136307 | B32: 712 | C32: 8 | D32: *SB* 20" Let It Snow Embossed Metal Framed Wall Art | E32: 048893214456 | F32: 93170 | G32: https://www.razimports.com/media/catalog_product/ImagesFiles2/4136307.jpg?quality=100&bg-color=255,255,255&fit=bounds&height=1000&width=1000&canvas=1000:1000 | H32: Made of METAL | I32: Measures: 20" L x 0.75" W x 20" H | J32: BLACK | K32: 19.50 | L32: (4EA) Minimum | M32: 10.45 | N32: (8EA) | O32: Artist: © Bex Morley
A33: 4216921 | B33: 670 | C33: 8 | D33: *SB* 11" Gnomes in Forest Lighted Water Lantern | E33: 048893384111 | F33: 93551 | G33: https://www.razimports.com/media/catalog_product/ImagesFiles2/4216921.jpg?quality=100&bg-color=255,255,255&fit=bounds&height=1000&width=1000&canvas=1000:1000 | H33: Made of PLASTIC | I33: Measures: 7" L x 3.25" W x 11" H | J33: BLACK | K33: 30.00 | L33: (4EA) Minimum | M33: 16.08 | N33: (8EA) | O33: REQUIRES 3 AA BATTERIES | P33: 6 HOUR TIMER REPEATS EVERY 18 HOURS | Q33: CONTINUOUS SWIRLING GLITTER, GENTLY FLIP TO LOOSEN GLITTER, TO AVOID DAMAGE DO NOT SHAKE | R33: INCLUDES USB CORD | S33: DOES NOT INCLUDE USB POWER ADAPTER | T33: DO NOT USE WITH USB POWER ADAPTER EXCEEDING 1.5 AMPS | U33: Artist: © Alexandria Designs, LLC
A34: F4202324 | B34: 660 | C34: 12 | D34: 31" Red Ball Ornament Spray | E34: 048893118587 | F34: 107600 | G34: https://www.razimports.com/media/catalog_product/ImagesFiles2/F4202324.jpg?quality=100&bg-color=255,255,255&fit=bounds&height=1000&width=1000&canvas=1000:1000 | H34: Made of PLASTIC | I34: Measures: 31" L | J34: RED | K34: 7.25 | L34: (12EA) Min. | M34: 6.10 | N34: (36EA) Case
A35: 4159136 | B35: 640 | C35: 16 | D35: *SB* 15.75" Christmas Message Block | E35: 048893217778 | F35: 93260 | G35: https://www.razimports.com/media/catalog_product/ImagesFiles2/4159136.jpg?quality=100&bg-color=255,255,255&fit=bounds&height=1000&width=1000&canvas=1000:1000 | H35: Made of FIR | I35: Measures: 15.75"L x 1.5"W x 3.25"H | J35: 2 ASST BLACK | K35: 7.40 | L35: (8EA) Minimum | M35: 4.00 | N35: (16EA) | O35: HANGS OR SITS | P35: Artist: © SAPNA; Licensed by SAPNA
A36: 4540514 | B36: 636 | C36: 4 | D36: 8" Cardinal and Birdhouse Lighted Water Lantern | E36: 048893943936 | F36: 103067 | G36: https://www.razimports.com/media/catalog_product/ImagesFiles2/4540514.jpg?quality=100&bg-color=255,255,255&fit=bounds&height=1000&width=1000&canvas=1000:1000 | H36: Made of PLASTIC | I36: Measures: 4.75" L x 3" W x 8" H | J36: BLACK | K36: 21.30 | L36: (4EA) Min. | M36: 18.85 | N36: (8EA) Case | O36: REQUIRES 3 AAA BATTERIES | P36: 6 HOUR TIMER REPEATS EVERY 18 HOURS | Q36: CONTINUOUS SWIRLING GLITTER, GENTLY FLIP TO LOOSEN GLITTER, TO AVOID DAMAGE DO NOT SHAKE | R36: INCLUDES USB CORD | S36: DOES NOT INCLUDE USB POWER ADAPTER | T36: DO NOT USE WITH USB POWER ADAPTER EXCEEDING 1.5 AMPS
A37: G4160801 | B37: 636 | C37: 6 | D37: 6' Felt Ball Garland | E37: 048893251239 | F37: 109826 | G37: https://www.razimports.com/media/catalog_product/ImagesFiles2/G4160801.jpg?quality=100&bg-color=255,255,255&fit=bounds&height=1000&width=1000&canvas=1000:1000 | H37: Made of POLYESTER | I37: Measures: 6' L | J37: RED | K37: 14.80 | L37: (6EA) Min. | M37: 12.55 | N37: (12EA) Case
A38: 4103430 | B38: 627 | C38: 12 | D38: *SB* 14.75" Posable Red and White Gnome | E38: 048893201456 | F38: 92912 | G38: https://www.razimports.com/media/catalog_product/ImagesFiles2/4103430.jpg?quality=100&bg-color=255,255,255&fit=bounds&height=1000&width=1000&canvas=1000:1000 | H38: Made of POLYESTER | I38: Measures: 9.5"L x 5.75"W x 14.75"H; 8.5"L x 7.5"W x 14.5"H; 8.5"L x 5.75"W x 14"H | J38: 3 ASST MULTICOLOR | K38: 21.70 | L38: (3EA) Minimum | M38: 11.10 | N38: (12EA) | O38: NOT INTENDED FOR CHILDREN | P38: FOR DECORATIVE USE ONLY
A39: 4559421 | B39: 624 | C39: 6 | D39: *DC* 3" X 6" Red Stripe Candle | E39: 048893429423 | F39: 104792 | G39: https://www.razimports.com/media/catalog_product/ImagesFiles2/4559421.jpg?quality=100&bg-color=255,255,255&fit=bounds&height=1000&width=1000&canvas=1000:1000 | H39: Made of PLASTIC | I39: Measures: 3" D x 6" H | J39: RED | K39: 9.65 | L39: (6EA) Min. | M39: 8.40 | N39: (12EA) Case | O39: REQUIRES 3 AAA BATTERIES | P39: 6 HOUR TIMER REPEATS EVERY 18 HOURS | Q39: BATTERY LIFE APPROX 120 HOURS | R39: REMOTE READY | S39: CAN BE USED WITH REMOTE #X4532915 | T39: DISCOUNTS CAPPED AT 10%
A40: F4516201 | B40: 624 | C40: 12 | D40: 29" Multicolor Ball Spray | E40: 048893938451 | F40: 108560 | G40: https://www.razimports.com/media/catalog_product/ImagesFiles2/F4516201.jpg?quality=100&bg-color=255,255,255&fit=bounds&height=1000&width=1000&canvas=1000:1000 | H40: Made of PLASTIC | I40: Measures: 29" L | J40: MULTICOLOR | K40: 6.65 | L40: (12EA) Min. | M40: 5.85 | N40: (24EA) Case
A41: 4512180 | B41: 606 | C41: 6 | D41: 5" Present Candle Holder | E41: 048893957315 | F41: 98318 | G41: https://www.razimports.com/media/catalog_product/ImagesFiles2/4512180.jpg?quality=100&bg-color=255,255,255&fit=bounds&height=1000&width=1000&canvas=1000:1000 | H41: Made of NATURAL STONE POWDER | I41: Measures: 4"L x 4.3"W x 2.75"H; 4"L x 4.25"W x 2.5"H; 5"L x 3.5"W x 2.5"H | J41: 3 ASST MULTICOLOR | K41: 9.00 | L41: (6EA) Min. | M41: 7.90 | N41: (12EA) Case | O41: FOR USE WITH BATTERY OPERATED CANDLE ONLY | P41: HOLDS TAPER CANDLE
A42: G4106696 | B42: 606 | C42: 12 | D42: *SB* 48" Holiday Game Letter Garland | E42: 048893250324 | F42: 109811 | G42: https://www.razimports.com/media/catalog_product/ImagesFiles2/G4106696.jpg?quality=100&bg-color=255,255,255&fit=bounds&height=1000&width=1000&canvas=1000:1000 | H42: Made of FOAM | I42: Measures: 48" L x 20" H | J42: IVORY | K42: 16.45 | L42: (3EA) Minimum | M42: 8.35 | N42: (12EA) | O42: Artist: © Geoff Allen, Represented by Ruth Levis
A43: 4159093 | B43: 604 | C43: 8 | D43: *SB* 15.75" Potted Tree with Chickadees Textured Paper on Wood Wall Art | E43: 048893217518 | F43: 93236 | G43: https://www.razimports.com/media/catalog_product/ImagesFiles2/4159093.jpg?quality=100&bg-color=255,255,255&fit=bounds&height=1000&width=1000&canvas=1000:1000 | H43: Made of FIR | I43: Measures: 12"L x 1.25"W x 15.75"H | J43: 2 ASST WHITE | K43: 13.50 | L43: (4EA) Minimum | M43: 7.20 | N43: (8EA) | O43: Artist: © Galaxy of Graphics Licensing LLC, Nan
A44: 4533533 | B44: 600 | C44: 12 | D44: 6" Clear Seamless Iridescent Ball | E44: 048893931308 | F44: 102743 | G44: https://www.razimports.com/media/catalog_product/ImagesFiles2/4533533.jpg?quality=100&bg-color=255,255,255&fit=bounds&height=1000&width=1000&canvas=1000:1000 | H44: Made of PET (POLYETHYLENE TEREPHTHALATE) | I44: Measures: 6" D | J44: CLEAR | K44: 6.25 | L44: (12EA) Min. | M44: 5.55 | N44: (24EA) Case
A45: 4159084 | B45: 592 | C45: 8 | D45: *SB* 12" Church Textured Paper Framed Wall Art | E45: 048893217457 | F45: 93233 | G45: https://www.razimports.com/media/catalog_product/ImagesFiles2/4159084.jpg?quality=100&bg-color=255,255,255&fit=bounds&height=1000&width=1000&canvas=1000:1000 | H45: Made of MDF | I45: Measures: 12"L x 1"W x 12"H | J45: 2 ASST MULTICOLOR | K45: 11.50 | L45: (4EA) Minimum | M45: 6.00 | N45: (8EA) | O45: Artist: © Danielle Murray
A46: F4542091 | B46: 588 | C46: 12 | D46: 34" Jeweled Spray | E46: 048893937034 | F46: 109031 | G46: https://www.razimports.com/media/catalog_product/ImagesFiles2/F4542091.jpg?quality=100&bg-color=255,255,255&fit=bounds&height=1000&width=1000&canvas=1000:1000 | H46: Made of PE (POLYETHYLENE) | I46: Measures: 34"L | J46: 2 ASST MULTICOLOR | K46: 5.50 | L46: (12EA) Min. | M46: 4.65 | N46: (36EA) Case
A47: G4516538 | B47: 588 | C47: 12 | D47: 15' X 0.5" Pink Beaded Garland | E47: 048893425791 | F47: 110108 | G47: https://www.razimports.com/media/catalog_product/ImagesFiles2/G4516538.jpg?quality=100&bg-color=255,255,255&fit=bounds&height=1000&width=1000&canvas=1000:1000 | H47: Made of PLASTIC | I47: Measures: 15' L | J47: PINK | K47: 6.30 | L47: (12EA) Min. | M47: 5.30 | N47: (48EA) Case | O47: 0.5" GIRTH
A48: 4019222 | B48: 570 | C48: 6 | D48: 8" Lighted Vintage Tree | E48: 048893164652 | F48: 92816 | G48: https://www.razimports.com/media/catalog_product/ImagesFiles2/4019222.jpg?quality=100&bg-color=255,255,255&fit=bounds&height=1000&width=1000&canvas=1000:1000 | H48: Made of PORCELAIN | I48: Measures: 5.5" D x 8" H | J48: GREEN | K48: 12.65 | L48: (6EA) Min. | M48: 11.50 | N48: (12EA) Case | O48: REQUIRES 2 AA BATTERIES | P48: 6 HOUR TIMER REPEATS EVERY 18 HOURS | Q48: Catalog (Christmas 2025) on page 87
A49: G4522990 | B49: 570 | C49: 6 | D49: 6' Multicolor Bead Garland | E49: 048893425609 | F49: 110162 | G49: https://www.razimports.com/media/catalog_product/ImagesFiles2/G4522990.jpg?quality=100&bg-color=255,255,255&fit=bounds&height=1000&width=1000&canvas=1000:1000 | H49: Made of GLASS | I49: Measures: 6' L | J49: MULTICOLOR | K49: 21.30 | L49: (6EA) Min. | M49: 18.95 | N49: (12EA) Case | O49: Catalog (Christmas 2025) on page 176
A50: 4559437 | B50: 568 | C50: 8 | D50: *DC* 8.5" Red Twist Taper Candles | E50: 048893429263 | F50: 104828 | G50: https://www.razimports.com/media/catalog_product/ImagesFiles2/4559437.jpg?quality=100&bg-color=255,255,255&fit=bounds&height=1000&width=1000&canvas=1000:1000 | H50: Made of PLASTIC | I50: Measures: 1"D x 8.5"H | J50: SET OF 2 RED | K50: 11.40 | L50: (8SET) Min. | M50: 10.10 | N50: (16SET) Case | O50: REQUIRES 2 AAA BATTERIES EACH | P50: 6 HOUR TIMER REPEATS EVERY 18 HOURS | Q50: BATTERY LIFE APPROX 120 HOURS | R50: REMOTE READY | S50: CAN BE USED WITH REMOTE #X4532915 | T50: DISCOUNTS CAPPED AT 10%
A51: G4517575 | B51: 564 | C51: 12 | D51: 5.5' Pearl and Crystal Beaded Garland | E51: 048893425722 | F51: 110129 | G51: https://www.razimports.com/media/catalog_product/ImagesFiles2/G4517575.jpg?quality=100&bg-color=255,255,255&fit=bounds&height=1000&width=1000&canvas=1000:1000 | H51: Made of PLASTIC | I51: Measures: 5.5' L | J51: WHITE - PEARL | K51: 8.80 | L51: (12EA) Min. | M51: 7.40 | N51: (36EA) Case
A52: 4559422 | B52: 558 | C52: 9 | D52: *DC* 2" X 4" Red Stripe Candle | E52: 048893429416 | F52: 104795 | G52: https://www.razimports.com/media/catalog_product/ImagesFiles2/4559422.jpg?quality=100&bg-color=255,255,255&fit=bounds&height=1000&width=1000&canvas=1000:1000 | H52: Made of PLASTIC | I52: Measures: 2" D x 4" H | J52: RED | K52: 7.65 | L52: (9EA) Min. | M52: 6.40 | N52: (18EA) Case | O52: REQUIRES 2 AA BATTERIES | P52: 6 HOUR TIMER REPEATS EVERY 18 HOURS | Q52: BATTERY LIFE APPROX 220 HOURS | R52: REMOTE READY | S52: CAN BE USED WITH REMOTE #X4532915 | T52: DISCOUNTS CAPPED AT 10%
A53: R4427786 | B53: 556 | C53: 4 | D53: 2.5" X 10 Yds Fuchsia Pink Velvet Ribbon | E53: 048893482824 | F53: 110525 | G53: https://www.razimports.com/media/catalog_product/ImagesFiles2/R4427786.jpg?quality=100&bg-color=255,255,255&fit=bounds&height=1000&width=1000&canvas=1000:1000 | H53: Made of POLYESTER | I53: Measures: 10YDS L x 2.5" W | J53: RED | K53: 23.40 | L53: (4EA) Min. | M53: 20.40 | N53: (8EA) Case
A54: 4559419 | B54: 540 | C54: 9 | D54: *DC* 3" X 4" Red Stripe Candle | E54: 048893429447 | F54: 104786 | G54: https://www.razimports.com/media/catalog_product/ImagesFiles2/4559419.jpg?quality=100&bg-color=255,255,255&fit=bounds&height=1000&width=1000&canvas=1000:1000 | H54: Made of PLASTIC | I54: Measures: 3" D x 4" H | J54: RED | K54: 8.70 | L54: (9EA) Min. | M54: 7.25 | N54: (18EA) Case | O54: REQUIRES 3 AAA BATTERIES | P54: 6 HOUR TIMER REPEATS EVERY 18 HOURS | Q54: BATTERY LIFE APPROX 120 HOURS | R54: REMOTE READY | S54: CAN BE USED WITH REMOTE #X4532915 | T54: DISCOUNTS CAPPED AT 10%
A55: 4559438 | B55: 536 | C55: 8 | D55: *DC* 10.5" Red Twist Taper Candles | E55: 048893429256 | F55: 104831 | G55: https://www.razimports.com/media/catalog_product/ImagesFiles2/4559438.jpg?quality=100&bg-color=255,255,255&fit=bounds&height=1000&width=1000&canvas=1000:1000 | H55: Made of PLASTIC | I55: Measures: 1"D x 10.5"H | J55: SET OF 2 RED | K55: 12.55 | L55: (8SET) Min. | M55: 11.15 | N55: (16SET) Case | O55: REQUIRES 2 AAA BATTERIES EACH | P55: 6 HOUR TIMER REPEATS EVERY 18 HOURS | Q55: BATTERY LIFE APPROX 120 HOURS | R55: REMOTE READY | S55: CAN BE USED WITH REMOTE #X4532915 | T55: DISCOUNTS CAPPED AT 10%
A56: 4324048 | B56: 516 | C56: 24 | D56: *SB* 2" X 6" Red Glass Ivory Pillar Candle | E56: 048893531126 | F56: 94466 | G56: https://www.razimports.com/media/catalog_product/ImagesFiles2/4324048.jpg?quality=100&bg-color=255,255,255&fit=bounds&height=1000&width=1000&canvas=1000:1000 | H56: Made of PLASTIC | I56: Measures: 2" D x 6" H | J56: RED | K56: 6.75 | L56: (12EA) Minimum | M56: 3.60 | N56: (24EA) | O56: REQUIRES 2 AA BATTERIES | P56: 6 HOUR TIMER REPEATS EVERY 18 HOURS | Q56: BATTERY LIFE APPROX 160 HOURS | R56: REMOTE READY | S56: CAN BE USED WITH REMOTE #X4324020
A57: 4536537 | B57: 508 | C57: 4 | D57: 16.5" Watercolor Holiday Snowman Framed Wall Art | E57: 048893433826 | F57: 102806 | G57: https://www.razimports.com/media/catalog_product/ImagesFiles2/4536537.jpg?quality=100&bg-color=255,255,255&fit=bounds&height=1000&width=1000&canvas=1000:1000 | H57: Made of FIR WOOD | I57: Measures: 12" L x 1" W x 16.5" H | J57: MULTICOLOR | K57: 16.70 | L57: (4EA) Min. | M57: 14.70 | N57: (8EA) Case | O57: Catalog (Christmas 2025) on page 349 | P57: Artist: © Susan Winget
A58: 4102652 | B58: 504 | C58: 24 | D58: *SB* 16" Snowman Posable Elf | E58: 048893254650 | F58: 92906 | G58: https://www.razimports.com/media/catalog_product/ImagesFiles2/4102652.jpg?quality=100&bg-color=255,255,255&fit=bounds&height=1000&width=1000&canvas=1000:1000 | H58: Made of POLYESTER | I58: Measures: 16" H | J58: MULTICOLOR | K58: 21.00 | L58: (4EA) Minimum | M58: 10.80 | N58: (24EA) | O58: NOT INTENDED FOR CHILDREN | P58: FOR DECORATIVE USE ONLY
A59: G4419031 | B59: 498 | C59: 6 | D59: 6' Pink and Silver Vintage Ornament Garland | E59: 048893483579 | F59: 109964 | G59: https://www.razimports.com/media/catalog_product/ImagesFiles2/G4419031.jpg?quality=100&bg-color=255,255,255&fit=bounds&height=1000&width=1000&canvas=1000:1000 | H59: Made of GLASS | I59: Measures: 6' L | J59: PINK | K59: 16.90 | L59: (6EA) Min. | M59: 14.90 | N59: (12EA) Case
A60: 4127988 | B60: 496 | C60: 8 | D60: *SB* 22" Dear Santa Textured Wood Wall Art | E60: 048893213657 | F60: 93119 | G60: https://www.razimports.com/media/catalog_product/ImagesFiles2/4127988.jpg?quality=100&bg-color=255,255,255&fit=bounds&height=1000&width=1000&canvas=1000:1000 | H60: Made of FIR WOOD | I60: Measures: 22" L x 2.5" W x 11" H | J60: MULTICOLOR | K60: 18.40 | L60: (4EA) Minimum | M60: 9.60 | N60: (8EA) | O60: Artist: © Jessica Mundo; Licensing by T.S.B. & C
A61: 4532888 | B61: 496 | C61: 8 | D61: 6" Through the Woods Ball Ornament | E61: 048893945114 | F61: 102524 | G61: https://www.razimports.com/media/catalog_product/ImagesFiles2/4532888.jpg?quality=100&bg-color=255,255,255&fit=bounds&height=1000&width=1000&canvas=1000:1000 | H61: Made of STYROFOAM | I61: Measures: 6" D | J61: MULTICOLOR | K61: 8.70 | L61: (8EA) Min. | M61: 7.60 | N61: (16EA) Case | O61: Catalog (Christmas 2025) on page 291 | P61: Artist: © Patty Rybolt, courtesy Wain's World Li
A62: F4506761 | B62: 492 | C62: 12 | D62: 21" Iced Blue Berry Pod Spray | E62: 048893427702 | F62: 108470 | G62: https://www.razimports.com/media/catalog_product/ImagesFiles2/F4506761.jpg?quality=100&bg-color=255,255,255&fit=bounds&height=1000&width=1000&canvas=1000:1000 | H62: Made of STYROFOAM | I62: Measures: 21" L | J62: BLUE - DARK | K62: 5.70 | L62: (12EA) Min. | M62: 4.80 | N62: (24EA) Case
A63: F4532784 | B63: 492 | C63: 12 | D63: 26" Multicolor Ball Spray | E63: 048893426804 | F63: 108815 | G63: https://www.razimports.com/media/catalog_product/ImagesFiles2/F4532784.jpg?quality=100&bg-color=255,255,255&fit=bounds&height=1000&width=1000&canvas=1000:1000 | H63: Made of PLASTIC | I63: Measures: 26" L | J63: MULTICOLOR | K63: 6.25 | L63: (12EA) Min. | M63: 5.55 | N63: (24EA) Case
A64: G4114104 | B64: 486 | C64: 6 | D64: 9.25' White Bead Garland | E64: 048893250447 | F64: 109817 | G64: https://www.razimports.com/media/catalog_product/ImagesFiles2/G4114104.jpg?quality=100&bg-color=255,255,255&fit=bounds&height=1000&width=1000&canvas=1000:1000 | H64: Made of HEDGE MAPLE | I64: Measures: 9.25' L | J64: WHITE | K64: 11.40 | L64: (6EA) Min. | M64: 9.80 | N64: (24EA) Case
A65: 4027940 | B65: 480 | C65: 6 | D65: *SB* 35" Sheet Music Wood Wall Art | E65: 048893167677 | F65: 92834 | G65: https://www.razimports.com/media/catalog_product/ImagesFiles2/4027940.jpg?quality=100&bg-color=255,255,255&fit=bounds&height=1000&width=1000&canvas=1000:1000 | H65: Made of FIR WOOD | I65: Measures: 28" L x 1.5" W x 35" H | J65: WHITE | K65: 45.00 | L65: (3EA) Minimum | M65: 24.00 | N65: (6EA) | O65: Artist: RAZ Art - No Royalty
A66: 4559420 | B66: 477 | C66: 9 | D66: *DC* 3" X 5" Red Stripe Candle | E66: 048893429430 | F66: 104789 | G66: https://www.razimports.com/media/catalog_product/ImagesFiles2/4559420.jpg?quality=100&bg-color=255,255,255&fit=bounds&height=1000&width=1000&canvas=1000:1000 | H66: Made of PLASTIC | I66: Measures: 3" D x 5" H | J66: RED | K66: 9.30 | L66: (9EA) Min. | M66: 7.75 | N66: (18EA) Case | O66: REQUIRES 3 AAA BATTERIES | P66: 6 HOUR TIMER REPEATS EVERY 18 HOURS | Q66: BATTERY LIFE APPROX 120 HOURS | R66: REMOTE READY | S66: CAN BE USED WITH REMOTE #X4532915 | T66: DISCOUNTS CAPPED AT 10%
A67: 4532887 | B67: 468 | C67: 12 | D67: 4" Through the Woods Ball Ornament | E67: 048893945121 | F67: 102521 | G67: https://www.razimports.com/media/catalog_product/ImagesFiles2/4532887.jpg?quality=100&bg-color=255,255,255&fit=bounds&height=1000&width=1000&canvas=1000:1000 | H67: Made of STYROFOAM | I67: Measures: 4" D | J67: MULTICOLOR | K67: 4.70 | L67: (12EA) Min. | M67: 4.10 | N67: (24EA) Case | O67: Catalog (Christmas 2025) on page 313 | P67: Artist: © Patty Rybolt, courtesy Wain's World Li
A68: F4206713 | B68: 468 | C68: 12 | D68: 42" Iced Ornament Ball and Snowy Pine Spray | E68: 048893981037 | F68: 107630 | G68: https://www.razimports.com/media/catalog_product/ImagesFiles2/F4206713.jpg?quality=100&bg-color=255,255,255&fit=bounds&height=1000&width=1000&canvas=1000:1000 | H68: Made of PLASTIC | I68: Measures: 42" L | J68: MULTICOLOR | K68: 9.85 | L68: (12EA) Min. | M68: 8.30 | N68: (36EA) Case
A69: 4512267 | B69: 464 | C69: 4 | D69: 10" Gingerbread Santa Tower | E69: 048893932442 | F69: 98507 | G69: https://www.razimports.com/media/catalog_product/ImagesFiles2/4512267.jpg?quality=100&bg-color=255,255,255&fit=bounds&height=1000&width=1000&canvas=1000:1000 | H69: Made of NATURAL STONE POWDER | I69: Measures: 7.25" L x 1.75" W x 10" H | J69: RED | K69: 11.55 | L69: (4EA) Min. | M69: 10.10 | N69: (8EA) Case
A70: 4512233 | B70: 464 | C70: 2 | D70: 10" Red and White Stripe Bow Candle Holders | E70: 048893956691 | F70: 98435 | G70: https://www.razimports.com/media/catalog_product/ImagesFiles2/4512233.jpg?quality=100&bg-color=255,255,255&fit=bounds&height=1000&width=1000&canvas=1000:1000 | H70: Made of NATURAL STONE POWDER | I70: Measures: 5.5"L x 4.5"W x 10"H; 4.5"L x 4"W x 7"H | J70: SET OF 2 RED | K70: 28.75 | L70: (2SET) Min. | M70: 25.55 | N70: (4SET) Case | O70: HOLDS UP TO 3" PILLAR CANDLE | P70: HOLDS TAPER CANDLE | Q70: Catalog (Christmas 2025) on page 18
A71: 4519206 | B71: 460 | C71: 4 | D71: 12" Lighted Snowman with Silver Swirling Glitter | E71: 048893952259 | F71: 99977 | G71: https://www.razimports.com/media/catalog_product/ImagesFiles2/4519206.jpg?quality=100&bg-color=255,255,255&fit=bounds&height=1000&width=1000&canvas=1000:1000 | H71: Made of PLASTIC | I71: Measures: 7.5" L x 4.75" W x 12" H | J71: MULTICOLOR | K71: 33.45 | L71: (4EA) Min. | M71: 29.60 | N71: (8EA) Case | O71: REQUIRES 3 AA BATTERIES | P71: 6 HOUR TIMER REPEATS EVERY 18 HOURS
A72: 4012325 | B72: 456 | C72: 12 | D72: *SB* 18" A Child Is Born Wall Art | E72: 048893158620 | F72: 92765 | G72: https://www.razimports.com/media/catalog_product/ImagesFiles2/4012325.jpg?quality=100&bg-color=255,255,255&fit=bounds&height=1000&width=1000&canvas=1000:1000 | H72: Made of WOOD (FIR) | I72: Measures: 14.5" L x 1" W x 18" H | J72: MULTICOLOR | K72: 13.40 | L72: (6EA) Minimum | M72: 7.05 | N72: (12EA) | O72: Artist: © SEPS: Licensed by Curtis Licensing. Al
A73: F4416123 | B73: 456 | C73: 12 | D73: 28" Iridescent Ball Spray | E73: 048893484309 | F73: 107867 | G73: https://www.razimports.com/media/catalog_product/ImagesFiles2/F4416123.jpg?quality=100&bg-color=255,255,255&fit=bounds&height=1000&width=1000&canvas=1000:1000 | H73: Made of PLASTIC | I73: Measures: 28" L | J73: MULTICOLOR | K73: 7.35 | L73: (12EA) Min. | M73: 6.55 | N73: (24EA) Case
A74: 4506677 | B74: 450 | C74: 6 | D74: 5.5" Box of 6 Bottle Brush Trees with Sprinkles | E74: 048893960247 | F74: 97010 | G74: https://www.razimports.com/media/catalog_product/ImagesFiles2/4506677.jpg?quality=100&bg-color=255,255,255&fit=bounds&height=1000&width=1000&canvas=1000:1000 | H74: Made of PLASTIC | I74: Measures: 2.5"D x 5.5"H | J74: BOX OF 6 MULTICOLOR | K74: 21.30 | L74: (6BOX) Min. | M74: 19.00 | N74: (12BOX) Case
A75: 4559406 | B75: 450 | C75: 6 | D75: 6.5" Gold Tree Candle | E75: 048893429577 | F75: 104756 | G75: https://www.razimports.com/media/catalog_product/ImagesFiles2/4559406.jpg?quality=100&bg-color=255,255,255&fit=bounds&height=1000&width=1000&canvas=1000:1000 | H75: Made of PLASTIC | I75: Measures: 4.25" D x 6.5" H | J75: GOLD - YELLOW | K75: 16.00 | L75: (6EA) Min. | M75: 14.10 | N75: (12EA) Case | O75: REQUIRES 3 AAA BATTERIES | P75: 6 HOUR TIMER REPEATS EVERY 18 HOURS | Q75: BATTERY LIFE APPROX 120 HOURS | R75: REMOTE READY | S75: CAN BE USED WITH REMOTE #X4532915
A76: F4322769 | B76: 448 | C76: 8 | D76: 47" Snowy Cedar Spray | E76: 048893537050 | F76: 107750 | G76: https://www.razimports.com/media/catalog_product/ImagesFiles2/F4322769.jpg?quality=100&bg-color=255,255,255&fit=bounds&height=1000&width=1000&canvas=1000:1000 | H76: Made of PVC (POLYVINYL CHLORIDE) | I76: Measures: 47" L | J76: GREEN | K76: 9.90 | L76: (8EA) Min. | M76: 8.75 | N76: (16EA) Case
A77: 4517612 | B77: 444 | C77: 4 | D77: 29.5" Dripping Pearl Trees | E77: 048893440862 | F77: 99701 | G77: https://www.razimports.com/media/catalog_product/ImagesFiles2/4517612.jpg?quality=100&bg-color=255,255,255&fit=bounds&height=1000&width=1000&canvas=1000:1000 | H77: Made of PLASTIC | I77: Measures: 11"L x 9.5"W x 29.5"H; 8"L x 7.5"W x 24.5"H | J77: SET OF 2 GOLD | K77: 47.20 | L77: (4SET) Min. | M77: 42.05 | N77: (8SET) Case | O77: Catalog (Christmas 2025) on page 236
A78: G4516200 | B78: 438 | C78: 6 | D78: 4' Multicolor Ball Garland | E78: 048893426019 | F78: 110081 | G78: https://www.razimports.com/media/catalog_product/ImagesFiles2/G4516200.jpg?quality=100&bg-color=255,255,255&fit=bounds&height=1000&width=1000&canvas=1000:1000 | H78: Made of PLASTIC | I78: Measures: 4' L | J78: MULTICOLOR | K78: 15.45 | L78: (6EA) Min. | M78: 13.65 | N78: (12EA) Case
A79: 3811194 | B79: 432 | C79: 4 | D79: 9.5" Gold Glitter Trees | E79: 048893222123 | F79: 92558 | G79: https://www.razimports.com/media/catalog_product/ImagesFiles2/3811194.jpg?quality=100&bg-color=255,255,255&fit=bounds&height=1000&width=1000&canvas=1000:1000 | H79: Made of NATURAL STONE POWDER | I79: Measures: 4"D x 9.5"H; 4"D x 7.5"H; 4"D x 6"H | J79: SET OF 3 GOLD | K79: 16.70 | L79: (4SET) Min. | M79: 14.90 | N79: (8SET) Case
A80: 4441222 | B80: 432 | C80: 36 | D80: 4" Matte Fuchsia Ball Ornament | E80: 048893487935 | F80: 96260 | G80: https://www.razimports.com/media/catalog_product/ImagesFiles2/4441222.jpg?quality=100&bg-color=255,255,255&fit=bounds&height=1000&width=1000&canvas=1000:1000 | H80: Made of PLASTIC | I80: Measures: 4" D | J80: PINK | K80: 2.25 | L80: (36EA) Min. | M80: 1.90 | N80: (72EA) Case
A81: 4533523 | B81: 432 | C81: 24 | D81: 4" Sapphire Seamless Iridescent Ball | E81: 048893931391 | F81: 102713 | G81: https://www.razimports.com/media/catalog_product/ImagesFiles2/4533523.jpg?quality=100&bg-color=255,255,255&fit=bounds&height=1000&width=1000&canvas=1000:1000 | H81: Made of PET (POLYETHYLENE TEREPHTHALATE) | I81: Measures: 4" D | J81: BLUE | K81: 2.75 | L81: (24EA) Min. | M81: 2.45 | N81: (48EA) Case | O81: Catalog (Christmas 2025) on page 439
A82: F4542092 | B82: 432 | C82: 12 | D82: 34" Pink Jewel Spray | E82: 048893937003 | F82: 109034 | G82: https://www.razimports.com/media/catalog_product/ImagesFiles2/F4542092.jpg?quality=100&bg-color=255,255,255&fit=bounds&height=1000&width=1000&canvas=1000:1000 | H82: Made of PE (POLYETHYLENE) | I82: Measures: 34" L | J82: PINK | K82: 5.50 | L82: (12EA) Min. | M82: 4.65 | N82: (36EA) Case
A83: G4516358 | B83: 432 | C83: 6 | D83: 6' Crystal Garland | E83: 048893425890 | F83: 110096 | G83: https://www.razimports.com/media/catalog_product/ImagesFiles2/G4516358.jpg?quality=100&bg-color=255,255,255&fit=bounds&height=1000&width=1000&canvas=1000:1000 | H83: Made of TIN SHEET | I83: Measures: 6' L | J83: CLEAR | K83: 17.95 | L83: (6EA) Min. | M83: 15.20 | N83: (24EA) Case | O83: Catalog (Christmas 2025) on page 221
A84: 4500782 | B84: 428 | C84: 4 | D84: 9" Cardinal Lighted Water Lantern | E84: 048893961336 | F84: 96659 | G84: https://www.razimports.com/media/catalog_product/ImagesFiles2/4500782.jpg?quality=100&bg-color=255,255,255&fit=bounds&height=1000&width=1000&canvas=1000:1000 | H84: Made of PLASTIC | I84: Measures: 4" L x 4" W x 9" H | J84: BLACK | K84: 23.45 | L84: (4EA) Min. | M84: 20.75 | N84: (8EA) Case | O84: REQUIRES 3 AAA BATTERIES | P84: 6 HOUR TIMER REPEATS EVERY 18 HOURS | Q84: CONTINUOUS SWIRLING GLITTER, GENTLY FLIP TO LOOSEN GLITTER, TO AVOID DAMAGE DO NOT SHAKE | R84: INCLUDES USB CORD | S84: DOES NOT INCLUDE USB POWER ADAPTER | T84: DO NOT USE WITH USB POWER ADAPTER EXCEEDING 1.5 AMPS
A85: 4559407 | B85: 426 | C85: 6 | D85: 7.75" Gold Tree Candle | E85: 048893429553 | F85: 104759 | G85: https://www.razimports.com/media/catalog_product/ImagesFiles2/4559407.jpg?quality=100&bg-color=255,255,255&fit=bounds&height=1000&width=1000&canvas=1000:1000 | H85: Made of PLASTIC | I85: Measures: 4.5" D x 7.75" H | J85: GOLD - YELLOW | K85: 18.10 | L85: (6EA) Min. | M85: 16.20 | N85: (12EA) Case | O85: REQUIRES 3 AAA BATTERIES | P85: 6 HOUR TIMER REPEATS EVERY 18 HOURS | Q85: BATTERY LIFE APPROX 120 HOURS | R85: REMOTE READY | S85: CAN BE USED WITH REMOTE #X4532915 | T85: DISCOUNTS CAPPED AT 10%
A86: G4513610 | B86: 426 | C86: 6 | D86: 6' Silver and Gold Beaded Garland | E86: 048893426033 | F86: 110069 | G86: https://www.razimports.com/media/catalog_product/ImagesFiles2/G4513610.jpg?quality=100&bg-color=255,255,255&fit=bounds&height=1000&width=1000&canvas=1000:1000 | H86: Made of PLASTIC | I86: Measures: 6' L | J86: GOLD | K86: 17.40 | L86: (6EA) Min. | M86: 14.75 | N86: (12EA) Case | O86: Catalog (Christmas 2025) on page 301
A87: X4159040 | B87: 424 | C87: 8 | D87: *SB* 5" Scalloped Candle Holders | E87: 048893254247 | F87: 111578 | G87: https://www.razimports.com/media/catalog_product/ImagesFiles2/X4159040.jpg?quality=100&bg-color=255,255,255&fit=bounds&height=1000&width=1000&canvas=1000:1000 | H87: Made of IRON | I87: Measures: 5"D x 4.25"H; 5"D x 4.75"H | J87: SET OF 2 GREY - SILVER | K87: 10.70 | L87: (4SET) Minimum | M87: 5.70 | N87: (8SET) | O87: HOLDS UP TO 4" PILLAR CANDLE
A88: 4134512 | B88: 420 | C88: 24 | D88: *SB* 3" x 7" Uyuni Red Pillar Candle | E88: 048893214265 | F88: 93152 | G88: https://www.razimports.com/media/catalog_product/ImagesFiles2/4134512.jpg?quality=100&bg-color=255,255,255&fit=bounds&height=1000&width=1000&canvas=1000:1000 | H88: Made of PARAFFIN | I88: Measures: 3" D x 7" H | J88: RED | K88: 16.80 | L88: (6EA) Minimum | M88: 9.00 | N88: (24EA) | O88: REQUIRES 2 C BATTERIES | P88: 6 HOUR TIMER REPEATS EVERY 18 HOURS | Q88: BATTERY LIFE APPROX 1,000 HOURS | R88: REMOTE READY | S88: CAN BE USED WITH REMOTE #X4034520 | T88: DISCOUNTS CAPPED AT 10%
A89: 4532885 | B89: 420 | C89: 12 | D89: 4" Stripe Ball Ornament | E89: 048893945152 | F89: 102515 | G89: https://www.razimports.com/media/catalog_product/ImagesFiles2/4532885.jpg?quality=100&bg-color=255,255,255&fit=bounds&height=1000&width=1000&canvas=1000:1000 | H89: Made of STYROFOAM | I89: Measures: 4" D | J89: MULTICOLOR | K89: 4.70 | L89: (12EA) Min. | M89: 4.10 | N89: (24EA) Case
A90: F4542143 | B90: 410 | C90: 10 | D90: 38" Champagne Butterfly Branch | E90: 048893930714 | F90: 109112 | G90: https://www.razimports.com/media/catalog_product/ImagesFiles2/F4542143.jpg?quality=100&bg-color=255,255,255&fit=bounds&height=1000&width=1000&canvas=1000:1000 | H90: Made of POLYESTER | I90: Measures: 38" L | J90: GOLD - CHAMPAGNE | K90: 6.10 | L90: (10EA) Min. | M90: 5.30 | N90: (20EA) Case
A91: 4159106 | B91: 408 | C91: 8 | D91: *SB* 17" Holiday Recipe Cutting Board | E91: 048893217594 | F91: 93245 | G91: https://www.razimports.com/media/catalog_product/ImagesFiles2/4159106.jpg?quality=100&bg-color=255,255,255&fit=bounds&height=1000&width=1000&canvas=1000:1000 | H91: Made of MDF | I91: Measures: 17"L x 1.25"W x 6.75"H | J91: 4 ASST BROWN - LIGHT | K91: 8.80 | L91: (4EA) Minimum | M91: 4.70 | N91: (8EA) | O91: FOR DECORATIVE USE ONLY | P91: Artist: © Pam Vale
A92: 4311337 | B92: 408 | C92: 2 | D92: 14" Pinecone Trees | E92: 048893558215 | F92: 94040 | G92: https://www.razimports.com/media/catalog_product/ImagesFiles2/4311337.jpg?quality=100&bg-color=255,255,255&fit=bounds&height=1000&width=1000&canvas=1000:1000 | H92: Made of NATURAL STONE POWDER | I92: Measures: 4.25"D x 14"H; 3.75"D x 11.5"H | J92: SET OF 2 BROWN | K92: 23.85 | L92: (2SET) Min. | M92: 20.25 | N92: (4SET) Case
A93: 4532886 | B93: 408 | C93: 8 | D93: 6" Stripe Ball Ornament | E93: 048893945145 | F93: 102518 | G93: https://www.razimports.com/media/catalog_product/ImagesFiles2/4532886.jpg?quality=100&bg-color=255,255,255&fit=bounds&height=1000&width=1000&canvas=1000:1000 | H93: Made of STYROFOAM | I93: Measures: 6" D | J93: MULTICOLOR | K93: 8.70 | L93: (8EA) Min. | M93: 7.60 | N93: (16EA) Case
A94: F4517580 | B94: 408 | C94: 12 | D94: 32" Multicolor Jeweled Spray | E94: 048893938079 | F94: 108596 | G94: https://www.razimports.com/media/catalog_product/ImagesFiles2/F4517580.jpg?quality=100&bg-color=255,255,255&fit=bounds&height=1000&width=1000&canvas=1000:1000 | H94: Made of PLASTIC | I94: Measures: 32" L | J94: MULTICOLOR | K94: 7.40 | L94: (12EA) Min. | M94: 6.25 | N94: (48EA) Case
A95: G4102342 | B95: 408 | C95: 24 | D95: *SB* 6' Ball Garland | E95: 048893250126 | F95: 109808 | G95: https://www.razimports.com/media/catalog_product/ImagesFiles2/G4102342.jpg?quality=100&bg-color=255,255,255&fit=bounds&height=1000&width=1000&canvas=1000:1000 | H95: Made of STYROFOAM | I95: Measures: 6' L | J95: MULTICOLOR | K95: 9.70 | L95: (6EA) Minimum | M95: 5.05 | N95: (24EA)
A96: G4006758 | B96: 400 | C96: 4 | D96: 5' Silver Glittered Beaded Garland | E96: 048893178369 | F96: 109799 | G96: https://www.razimports.com/media/catalog_product/ImagesFiles2/G4006758.jpg?quality=100&bg-color=255,255,255&fit=bounds&height=1000&width=1000&canvas=1000:1000 | H96: Made of PLASTIC | I96: Measures: 5' L | J96: GREY - SILVER | K96: 10.65 | L96: (4EA) Min. | M96: 9.05 | N96: (24EA) Case
A97: 4516699 | B97: 398 | C97: 2 | D97: 31.5" Champagne Vine Wrapped Cone Trees | E97: 048893441098 | F97: 99428 | G97: https://www.razimports.com/media/catalog_product/ImagesFiles2/4516699.jpg?quality=100&bg-color=255,255,255&fit=bounds&height=1000&width=1000&canvas=1000:1000 | H97: Made of WIRE | I97: Measures: 8"D x 31.5"H; 6.5"D x 23.5"H; 5"D x 15.5"H | J97: SET OF 3 GOLD - CHAMPAGNE | K97: 37.05 | L97: (2SET) Min. | M97: 32.90 | N97: (4SET) Case
A98: 4536539 | B98: 396 | C98: 4 | D98: 16.5" Watercolor Holiday Santa Framed Wall Art | E98: 048893433802 | F98: 102812 | G98: https://www.razimports.com/media/catalog_product/ImagesFiles2/4536539.jpg?quality=100&bg-color=255,255,255&fit=bounds&height=1000&width=1000&canvas=1000:1000 | H98: Made of FIR WOOD | I98: Measures: 12" L x 1" W x 16.5" H | J98: MULTICOLOR | K98: 16.70 | L98: (4EA) Min. | M98: 14.70 | N98: (8EA) Case | O98: Catalog (Christmas 2025) on page 349 | P98: Artist: © Susan Winget
A99: F4102485 | B99: 396 | C99: 36 | D99: *SB* 18" Rose and Berry Pick | E99: 048893218591 | F99: 107570 | G99: https://www.razimports.com/media/catalog_product/ImagesFiles2/F4102485.jpg?quality=100&bg-color=255,255,255&fit=bounds&height=1000&width=1000&canvas=1000:1000 | H99: Made of PLASTIC | I99: Measures: 18" L | J99: RED | K99: 8.55 | L99: (12EA) Minimum | M99: 4.45 | N99: (36EA)
A100: 4510505 | B100: 394 | C100: 4 | D100: 15" Santa Plate | E100: 048893445591 | F100: 97646 | G100: https://www.razimports.com/media/catalog_product/ImagesFiles2/4510505.jpg?quality=100&bg-color=255,255,255&fit=bounds&height=1000&width=1000&canvas=1000:1000 | H100: Made of DOLOMITE | I100: Measures: 15.25" L x 6.25" W x 1.25" H | J100: MULTICOLOR | K100: 15.10 | L100: (4EA) Min. | M100: 13.30 | N100: (8EA) Case | O100: FOOD SAFE | P100: Artist: © Tina Higgins Design, Courtesy of MHS L
...

Sheet Stats
A1: sku | B1: qty_available | C1: min_order_qty | D1: MinCase | E1: IsOnSale | F1: Cases Available | G1: IsGreaterThan10 | H1: MinCaseCost | I1: MaxCaseCost | J1: TrueCost | K1: Amazon Cost | L1: UPC | M1: BareUPC | N1: Tier1RawGTIN | O1: Tier2RawGTIN | P1: Tier1GTIN | Q1: Tier2GTIN
A2: G3216179 | B2: =VLOOKUP(A2, Sheet1!A:Z, 2, FALSE) -> 2232 | C2: =VALUE(VLOOKUP(A2, Sheet1!A:Z, 3, FALSE)) -> 6 | D2: {=--_xlfn.TEXTJOIN("",TRUE,IF(ISNUMBER(MID(LEFT(MID(VLOOKUP(A2,Sheet1!A:Z,12,FALSE),2,99),FIND(")",VLOOKUP(A2,Sheet1!A:Z,12,FALSE))-2),ROW($1:$20),1)+0),MID(LEFT(MID(VLOOKUP(A2,Sheet1!A:Z,12,FALSE),2,99),FIND(")",VLOOKUP(A2,Sheet1!A:Z,12,FALSE))-2),ROW($1:$20),1),""))} -> 6 | E2: =IF(ISNUMBER(SEARCH("Minimum", VLOOKUP(A2, Sheet1!A:Z, 12, FALSE))), TRUE, FALSE) -> FALSE | F2: =QUOTIENT(B2, C2) -> 372 | G2: =VALUE(VLOOKUP(A2, Sheet1!A:Z, 11, FALSE))>=10 -> TRUE | H2: =VLOOKUP(A2, Sheet1!A:Z, 11, FALSE) -> 14.25 | I2: =VLOOKUP(A2, Sheet1!A:Z, 13, FALSE) -> 12.60 | J2: =IF(E2, I2, IF(C2<>D2,I2,H2)) -> 14.25 | K2: =(J2+20%)*2.8 -> 40.46 | L2: =VLOOKUP(A2, Sheet1!A:Z, 5, FALSE) -> 048893851880 | M2: =LEFT(L2, LEN(L2)-1) -> 04889385188 | N2: =(3000000000000+M2) -> 3004889385188 | O2: =(5000000000000+M2) -> 5004889385188 | P2: {=N2 & MOD(10 - MOD(SUMPRODUCT(MID(N2, ROW(INDIRECT("1:" & LEN(N2))), 1) * IF(MOD(ROW(INDIRECT("1:" & LEN(N2))), 2) = 0, 1, 3)), 10), 10)} -> 30048893851881
A3: 3911406 | B3: =VLOOKUP(A3, Sheet1!A:Z, 2, FALSE) -> 2082 | C3: =VALUE(VLOOKUP(A3, Sheet1!A:Z, 3, FALSE)) -> 2 | D3: {=--_xlfn.TEXTJOIN("",TRUE,IF(ISNUMBER(MID(LEFT(MID(VLOOKUP(A3,Sheet1!A:Z,12,FALSE),2,99),FIND(")",VLOOKUP(A3,Sheet1!A:Z,12,FALSE))-2),ROW($1:$20),1)+0),MID(LEFT(MID(VLOOKUP(A3,Sheet1!A:Z,12,FALSE),2,99),FIND(")",VLOOKUP(A3,Sheet1!A:Z,12,FALSE))-2),ROW($1:$20),1),""))} -> 2 | E3: =IF(ISNUMBER(SEARCH("Minimum", VLOOKUP(A3, Sheet1!A:Z, 12, FALSE))), TRUE, FALSE) -> FALSE | F3: =QUOTIENT(B3, C3) -> 1041 | G3: =VALUE(VLOOKUP(A3, Sheet1!A:Z, 11, FALSE))>=10 -> TRUE | H3: =VLOOKUP(A3, Sheet1!A:Z, 11, FALSE) -> 31.40 | I3: =VLOOKUP(A3, Sheet1!A:Z, 13, FALSE) -> 27.70 | J3: =IF(E3, I3, IF(C3<>D3,I3,H3)) -> 31.40 | K3: =(J3+20%)*2.8 -> 88.48 | L3: =VLOOKUP(A3, Sheet1!A:Z, 5, FALSE) -> 048893073978 | M3: =LEFT(L3, LEN(L3)-1) -> 04889307397 | N3: =(3000000000000+M3) -> 3004889307397 | O3: =(5000000000000+M3) -> 5004889307397 | P3: {=N3 & MOD(10 - MOD(SUMPRODUCT(MID(N3, ROW(INDIRECT("1:" & LEN(N3))), 1) * IF(MOD(ROW(INDIRECT("1:" & LEN(N3))), 2) = 0, 1, 3)), 10), 10)} -> 30048893073979
A4: G3416336 | B4: =VLOOKUP(A4, Sheet1!A:Z, 2, FALSE) -> 1920 | C4: =VALUE(VLOOKUP(A4, Sheet1!A:Z, 3, FALSE)) -> 6 | D4: {=--_xlfn.TEXTJOIN("",TRUE,IF(ISNUMBER(MID(LEFT(MID(VLOOKUP(A4,Sheet1!A:Z,12,FALSE),2,99),FIND(")",VLOOKUP(A4,Sheet1!A:Z,12,FALSE))-2),ROW($1:$20),1)+0),MID(LEFT(MID(VLOOKUP(A4,Sheet1!A:Z,12,FALSE),2,99),FIND(")",VLOOKUP(A4,Sheet1!A:Z,12,FALSE))-2),ROW($1:$20),1),""))} -> 6 | E4: =IF(ISNUMBER(SEARCH("Minimum", VLOOKUP(A4, Sheet1!A:Z, 12, FALSE))), TRUE, FALSE) -> FALSE | F4: =QUOTIENT(B4, C4) -> 320 | G4: =VALUE(VLOOKUP(A4, Sheet1!A:Z, 11, FALSE))>=10 -> TRUE | H4: =VLOOKUP(A4, Sheet1!A:Z, 11, FALSE) -> 14.90 | I4: =VLOOKUP(A4, Sheet1!A:Z, 13, FALSE) -> 13.20 | J4: =IF(E4, I4, IF(C4<>D4,I4,H4)) -> 14.90 | K4: =(J4+20%)*2.8 -> 42.28 | L4: =VLOOKUP(A4, Sheet1!A:Z, 5, FALSE) -> 048893987831 | M4: =LEFT(L4, LEN(L4)-1) -> 04889398783 | N4: =(3000000000000+M4) -> 3004889398783 | O4: =(5000000000000+M4) -> 5004889398783 | P4: {=N4 & MOD(10 - MOD(SUMPRODUCT(MID(N4, ROW(INDIRECT("1:" & LEN(N4))), 1) * IF(MOD(ROW(INDIRECT("1:" & LEN(N4))), 2) = 0, 1, 3)), 10), 10)} -> 30048893987832
A5: 4559488 | B5: =VLOOKUP(A5, Sheet1!A:Z, 2, FALSE) -> 1592 | C5: =VALUE(VLOOKUP(A5, Sheet1!A:Z, 3, FALSE)) -> 8 | D5: {=--_xlfn.TEXTJOIN("",TRUE,IF(ISNUMBER(MID(LEFT(MID(VLOOKUP(A5,Sheet1!A:Z,12,FALSE),2,99),FIND(")",VLOOKUP(A5,Sheet1!A:Z,12,FALSE))-2),ROW($1:$20),1)+0),MID(LEFT(MID(VLOOKUP(A5,Sheet1!A:Z,12,FALSE),2,99),FIND(")",VLOOKUP(A5,Sheet1!A:Z,12,FALSE))-2),ROW($1:$20),1),""))} -> 8 | E5: =IF(ISNUMBER(SEARCH("Minimum", VLOOKUP(A5, Sheet1!A:Z, 12, FALSE))), TRUE, FALSE) -> FALSE | F5: =QUOTIENT(B5, C5) -> 199 | G5: =VALUE(VLOOKUP(A5, Sheet1!A:Z, 11, FALSE))>=10 -> TRUE | H5: =VLOOKUP(A5, Sheet1!A:Z, 11, FALSE) -> 16.00 | I5: =VLOOKUP(A5, Sheet1!A:Z, 13, FALSE) -> 14.40 | J5: =IF(E5, I5, IF(C5<>D5,I5,H5)) -> 16.00 | K5: =(J5+20%)*2.8 -> 45.36 | L5: =VLOOKUP(A5, Sheet1!A:Z, 5, FALSE) -> 048893931223 | M5: =LEFT(L5, LEN(L5)-1) -> 04889393122 | N5: =(3000000000000+M5) -> 3004889393122 | O5: =(5000000000000+M5) -> 5004889393122 | P5: {=N5 & MOD(10 - MOD(SUMPRODUCT(MID(N5, ROW(INDIRECT("1:" & LEN(N5))), 1) * IF(MOD(ROW(INDIRECT("1:" & LEN(N5))), 2) = 0, 1, 3)), 10), 10)} -> 30048893931224
A6: 4533532 | B6: =VLOOKUP(A6, Sheet1!A:Z, 2, FALSE) -> 1536 | C6: =VALUE(VLOOKUP(A6, Sheet1!A:Z, 3, FALSE)) -> 24 | D6: {=--_xlfn.TEXTJOIN("",TRUE,IF(ISNUMBER(MID(LEFT(MID(VLOOKUP(A6,Sheet1!A:Z,12,FALSE),2,99),FIND(")",VLOOKUP(A6,Sheet1!A:Z,12,FALSE))-2),ROW($1:$20),1)+0),MID(LEFT(MID(VLOOKUP(A6,Sheet1!A:Z,12,FALSE),2,99),FIND(")",VLOOKUP(A6,Sheet1!A:Z,12,FALSE))-2),ROW($1:$20),1),""))} -> 24 | E6: =IF(ISNUMBER(SEARCH("Minimum", VLOOKUP(A6, Sheet1!A:Z, 12, FALSE))), TRUE, FALSE) -> FALSE | F6: =QUOTIENT(B6, C6) -> 64 | G6: =VALUE(VLOOKUP(A6, Sheet1!A:Z, 11, FALSE))>=10 -> FALSE | H6: =VLOOKUP(A6, Sheet1!A:Z, 11, FALSE) -> 2.75 | I6: =VLOOKUP(A6, Sheet1!A:Z, 13, FALSE) -> 2.45 | J6: =IF(E6, I6, IF(C6<>D6,I6,H6)) -> 2.75 | K6: =(J6+20%)*2.8 -> 8.26 | L6: =VLOOKUP(A6, Sheet1!A:Z, 5, FALSE) -> 048893931292 | M6: =LEFT(L6, LEN(L6)-1) -> 04889393129 | N6: =(3000000000000+M6) -> 3004889393129 | O6: =(5000000000000+M6) -> 5004889393129 | P6: {=N6 & MOD(10 - MOD(SUMPRODUCT(MID(N6, ROW(INDIRECT("1:" & LEN(N6))), 1) * IF(MOD(ROW(INDIRECT("1:" & LEN(N6))), 2) = 0, 1, 3)), 10), 10)} -> 30048893931293
A7: 4124532 | B7: =VLOOKUP(A7, Sheet1!A:Z, 2, FALSE) -> 1212 | C7: =VALUE(VLOOKUP(A7, Sheet1!A:Z, 3, FALSE)) -> 24 | D7: {=--_xlfn.TEXTJOIN("",TRUE,IF(ISNUMBER(MID(LEFT(MID(VLOOKUP(A7,Sheet1!A:Z,12,FALSE),2,99),FIND(")",VLOOKUP(A7,Sheet1!A:Z,12,FALSE))-2),ROW($1:$20),1)+0),MID(LEFT(MID(VLOOKUP(A7,Sheet1!A:Z,12,FALSE),2,99),FIND(")",VLOOKUP(A7,Sheet1!A:Z,12,FALSE))-2),ROW($1:$20),1),""))} -> 6 | E7: =IF(ISNUMBER(SEARCH("Minimum", VLOOKUP(A7, Sheet1!A:Z, 12, FALSE))), TRUE, FALSE) -> TRUE | F7: =QUOTIENT(B7, C7) -> 50 | G7: =VALUE(VLOOKUP(A7, Sheet1!A:Z, 11, FALSE))>=10 -> FALSE | H7: =VLOOKUP(A7, Sheet1!A:Z, 11, FALSE) -> 7.00 | I7: =VLOOKUP(A7, Sheet1!A:Z, 13, FALSE) -> 3.60 | J7: =IF(E7, I7, IF(C7<>D7,I7,H7)) -> 3.60 | K7: =(J7+20%)*2.8 -> 10.64 | L7: =VLOOKUP(A7, Sheet1!A:Z, 5, FALSE) -> 048893212469 | M7: =LEFT(L7, LEN(L7)-1) -> 04889321246 | N7: =(3000000000000+M7) -> 3004889321246 | O7: =(5000000000000+M7) -> 5004889321246 | P7: {=N7 & MOD(10 - MOD(SUMPRODUCT(MID(N7, ROW(INDIRECT("1:" & LEN(N7))), 1) * IF(MOD(ROW(INDIRECT("1:" & LEN(N7))), 2) = 0, 1, 3)), 10), 10)} -> 30048893212460
A8: 4432922 | B8: =VLOOKUP(A8, Sheet1!A:Z, 2, FALSE) -> 1200 | C8: =VALUE(VLOOKUP(A8, Sheet1!A:Z, 3, FALSE)) -> 8 | D8: {=--_xlfn.TEXTJOIN("",TRUE,IF(ISNUMBER(MID(LEFT(MID(VLOOKUP(A8,Sheet1!A:Z,12,FALSE),2,99),FIND(")",VLOOKUP(A8,Sheet1!A:Z,12,FALSE))-2),ROW($1:$20),1)+0),MID(LEFT(MID(VLOOKUP(A8,Sheet1!A:Z,12,FALSE),2,99),FIND(")",VLOOKUP(A8,Sheet1!A:Z,12,FALSE))-2),ROW($1:$20),1),""))} -> 8 | E8: =IF(ISNUMBER(SEARCH("Minimum", VLOOKUP(A8, Sheet1!A:Z, 12, FALSE))), TRUE, FALSE) -> FALSE | F8: =QUOTIENT(B8, C8) -> 150 | G8: =VALUE(VLOOKUP(A8, Sheet1!A:Z, 11, FALSE))>=10 -> TRUE | H8: =VLOOKUP(A8, Sheet1!A:Z, 11, FALSE) -> 15.45 | I8: =VLOOKUP(A8, Sheet1!A:Z, 13, FALSE) -> 13.85 | J8: =IF(E8, I8, IF(C8<>D8,I8,H8)) -> 15.45 | K8: =(J8+20%)*2.8 -> 43.82 | L8: =VLOOKUP(A8, Sheet1!A:Z, 5, FALSE) -> 048893490805 | M8: =LEFT(L8, LEN(L8)-1) -> 04889349080 | N8: =(3000000000000+M8) -> 3004889349080 | O8: =(5000000000000+M8) -> 5004889349080 | P8: {=N8 & MOD(10 - MOD(SUMPRODUCT(MID(N8, ROW(INDIRECT("1:" & LEN(N8))), 1) * IF(MOD(ROW(INDIRECT("1:" & LEN(N8))), 2) = 0, 1, 3)), 10), 10)} -> 30048893490806
A9: 4324035 | B9: =VLOOKUP(A9, Sheet1!A:Z, 2, FALSE) -> 1180 | C9: =VALUE(VLOOKUP(A9, Sheet1!A:Z, 3, FALSE)) -> 10 | D9: {=--_xlfn.TEXTJOIN("",TRUE,IF(ISNUMBER(MID(LEFT(MID(VLOOKUP(A9,Sheet1!A:Z,12,FALSE),2,99),FIND(")",VLOOKUP(A9,Sheet1!A:Z,12,FALSE))-2),ROW($1:$20),1)+0),MID(LEFT(MID(VLOOKUP(A9,Sheet1!A:Z,12,FALSE),2,99),FIND(")",VLOOKUP(A9,Sheet1!A:Z,12,FALSE))-2),ROW($1:$20),1),""))} -> 10 | E9: =IF(ISNUMBER(SEARCH("Minimum", VLOOKUP(A9, Sheet1!A:Z, 12, FALSE))), TRUE, FALSE) -> FALSE | F9: =QUOTIENT(B9, C9) -> 118 | G9: =VALUE(VLOOKUP(A9, Sheet1!A:Z, 11, FALSE))>=10 -> TRUE | H9: =VLOOKUP(A9, Sheet1!A:Z, 11, FALSE) -> 20.75 | I9: =VLOOKUP(A9, Sheet1!A:Z, 13, FALSE) -> 18.55 | J9: =IF(E9, I9, IF(C9<>D9,I9,H9)) -> 20.75 | K9: =(J9+20%)*2.8 -> 58.66 | L9: =VLOOKUP(A9, Sheet1!A:Z, 5, FALSE) -> 048893546533 | M9: =LEFT(L9, LEN(L9)-1) -> 04889354653 | N9: =(3000000000000+M9) -> 3004889354653 | O9: =(5000000000000+M9) -> 5004889354653 | P9: {=N9 & MOD(10 - MOD(SUMPRODUCT(MID(N9, ROW(INDIRECT("1:" & LEN(N9))), 1) * IF(MOD(ROW(INDIRECT("1:" & LEN(N9))), 2) = 0, 1, 3)), 10), 10)} -> 30048893546534
A10: F4517615 | B10: =VLOOKUP(A10, Sheet1!A:Z, 2, FALSE) -> 1140 | C10: =VALUE(VLOOKUP(A10, Sheet1!A:Z, 3, FALSE)) -> 12 | D10: {=--_xlfn.TEXTJOIN("",TRUE,IF(ISNUMBER(MID(LEFT(MID(VLOOKUP(A10,Sheet1!A:Z,12,FALSE),2,99),FIND(")",VLOOKUP(A10,Sheet1!A:Z,12,FALSE))-2),ROW($1:$20),1)+0),MID(LEFT(MID(VLOOKUP(A10,Sheet1!A:Z,12,FALSE),2,99),FIND(")",VLOOKUP(A10,Sheet1!A:Z,12,FALSE))-2),ROW($1:$20),1),""))} -> 12 | E10: =IF(ISNUMBER(SEARCH("Minimum", VLOOKUP(A10, Sheet1!A:Z, 12, FALSE))), TRUE, FALSE) -> FALSE | F10: =QUOTIENT(B10, C10) -> 95 | G10: =VALUE(VLOOKUP(A10, Sheet1!A:Z, 11, FALSE))>=10 -> FALSE | H10: =VLOOKUP(A10, Sheet1!A:Z, 11, FALSE) -> 8.70 | I10: =VLOOKUP(A10, Sheet1!A:Z, 13, FALSE) -> 7.25 | J10: =IF(E10, I10, IF(C10<>D10,I10,H10)) -> 8.70 | K10: =(J10+20%)*2.8 -> 24.92 | L10: =VLOOKUP(A10, Sheet1!A:Z, 5, FALSE) -> 048893937966 | M10: =LEFT(L10, LEN(L10)-1) -> 04889393796 | N10: =(3000000000000+M10) -> 3004889393796 | O10: =(5000000000000+M10) -> 5004889393796 | P10: {=N10 & MOD(10 - MOD(SUMPRODUCT(MID(N10, ROW(INDIRECT("1:" & LEN(N10))), 1) * IF(MOD(ROW(INDIRECT("1:" & LEN(N10))), 2) = 0, 1, 3)), 10), 10)} -> 30048893937967
A11: G4516359 | B11: =VLOOKUP(A11, Sheet1!A:Z, 2, FALSE) -> 1104 | C11: =VALUE(VLOOKUP(A11, Sheet1!A:Z, 3, FALSE)) -> 12 | D11: {=--_xlfn.TEXTJOIN("",TRUE,IF(ISNUMBER(MID(LEFT(MID(VLOOKUP(A11,Sheet1!A:Z,12,FALSE),2,99),FIND(")",VLOOKUP(A11,Sheet1!A:Z,12,FALSE))-2),ROW($1:$20),1)+0),MID(LEFT(MID(VLOOKUP(A11,Sheet1!A:Z,12,FALSE),2,99),FIND(")",VLOOKUP(A11,Sheet1!A:Z,12,FALSE))-2),ROW($1:$20),1),""))} -> 12 | E11: =IF(ISNUMBER(SEARCH("Minimum", VLOOKUP(A11, Sheet1!A:Z, 12, FALSE))), TRUE, FALSE) -> FALSE | F11: =QUOTIENT(B11, C11) -> 92 | G11: =VALUE(VLOOKUP(A11, Sheet1!A:Z, 11, FALSE))>=10 -> TRUE | H11: =VLOOKUP(A11, Sheet1!A:Z, 11, FALSE) -> 10.35 | I11: =VLOOKUP(A11, Sheet1!A:Z, 13, FALSE) -> 8.95 | J11: =IF(E11, I11, IF(C11<>D11,I11,H11)) -> 10.35 | K11: =(J11+20%)*2.8 -> 29.54 | L11: =VLOOKUP(A11, Sheet1!A:Z, 5, FALSE) -> 048893425883 | M11: =LEFT(L11, LEN(L11)-1) -> 04889342588 | N11: =(3000000000000+M11) -> 3004889342588 | O11: =(5000000000000+M11) -> 5004889342588 | P11: {=N11 & MOD(10 - MOD(SUMPRODUCT(MID(N11, ROW(INDIRECT("1:" & LEN(N11))), 1) * IF(MOD(ROW(INDIRECT("1:" & LEN(N11))), 2) = 0, 1, 3)), 10), 10)} -> 30048893425884
A12: G4416416 | B12: =VLOOKUP(A12, Sheet1!A:Z, 2, FALSE) -> 1080 | C12: =VALUE(VLOOKUP(A12, Sheet1!A:Z, 3, FALSE)) -> 12 | D12: {=--_xlfn.TEXTJOIN("",TRUE,IF(ISNUMBER(MID(LEFT(MID(VLOOKUP(A12,Sheet1!A:Z,12,FALSE),2,99),FIND(")",VLOOKUP(A12,Sheet1!A:Z,12,FALSE))-2),ROW($1:$20),1)+0),MID(LEFT(MID(VLOOKUP(A12,Sheet1!A:Z,12,FALSE),2,99),FIND(")",VLOOKUP(A12,Sheet1!A:Z,12,FALSE))-2),ROW($1:$20),1),""))} -> 12 | E12: =IF(ISNUMBER(SEARCH("Minimum", VLOOKUP(A12, Sheet1!A:Z, 12, FALSE))), TRUE, FALSE) -> FALSE | F12: =QUOTIENT(B12, C12) -> 90 | G12: =VALUE(VLOOKUP(A12, Sheet1!A:Z, 11, FALSE))>=10 -> FALSE | H12: =VLOOKUP(A12, Sheet1!A:Z, 11, FALSE) -> 6.30 | I12: =VLOOKUP(A12, Sheet1!A:Z, 13, FALSE) -> 5.30 | J12: =IF(E12, I12, IF(C12<>D12,I12,H12)) -> 6.30 | K12: =(J12+20%)*2.8 -> 18.2 | L12: =VLOOKUP(A12, Sheet1!A:Z, 5, FALSE) -> 048893986865 | M12: =LEFT(L12, LEN(L12)-1) -> 04889398686 | N12: =(3000000000000+M12) -> 3004889398686 | O12: =(5000000000000+M12) -> 5004889398686 | P12: {=N12 & MOD(10 - MOD(SUMPRODUCT(MID(N12, ROW(INDIRECT("1:" & LEN(N12))), 1) * IF(MOD(ROW(INDIRECT("1:" & LEN(N12))), 2) = 0, 1, 3)), 10), 10)} -> 30048893986866
A13: G4516540 | B13: =VLOOKUP(A13, Sheet1!A:Z, 2, FALSE) -> 1056 | C13: =VALUE(VLOOKUP(A13, Sheet1!A:Z, 3, FALSE)) -> 12 | D13: {=--_xlfn.TEXTJOIN("",TRUE,IF(ISNUMBER(MID(LEFT(MID(VLOOKUP(A13,Sheet1!A:Z,12,FALSE),2,99),FIND(")",VLOOKUP(A13,Sheet1!A:Z,12,FALSE))-2),ROW($1:$20),1)+0),MID(LEFT(MID(VLOOKUP(A13,Sheet1!A:Z,12,FALSE),2,99),FIND(")",VLOOKUP(A13,Sheet1!A:Z,12,FALSE))-2),ROW($1:$20),1),""))} -> 12 | E13: =IF(ISNUMBER(SEARCH("Minimum", VLOOKUP(A13, Sheet1!A:Z, 12, FALSE))), TRUE, FALSE) -> FALSE | F13: =QUOTIENT(B13, C13) -> 88 | G13: =VALUE(VLOOKUP(A13, Sheet1!A:Z, 11, FALSE))>=10 -> FALSE | H13: =VLOOKUP(A13, Sheet1!A:Z, 11, FALSE) -> 6.30 | I13: =VLOOKUP(A13, Sheet1!A:Z, 13, FALSE) -> 5.30 | J13: =IF(E13, I13, IF(C13<>D13,I13,H13)) -> 6.30 | K13: =(J13+20%)*2.8 -> 18.2 | L13: =VLOOKUP(A13, Sheet1!A:Z, 5, FALSE) -> 048893425814 | M13: =LEFT(L13, LEN(L13)-1) -> 04889342581 | N13: =(3000000000000+M13) -> 3004889342581 | O13: =(5000000000000+M13) -> 5004889342581 | P13: {=N13 & MOD(10 - MOD(SUMPRODUCT(MID(N13, ROW(INDIRECT("1:" & LEN(N13))), 1) * IF(MOD(ROW(INDIRECT("1:" & LEN(N13))), 2) = 0, 1, 3)), 10), 10)} -> 30048893425815
... A1096: 4159123 | B1096: =VLOOKUP(A1096, Sheet1!A:Z, 2, FALSE) -> 3 | C1096: =VALUE(VLOOKUP(A1096, Sheet1!A:Z, 3, FALSE)) -> 6 | D1096: {=--_xlfn.TEXTJOIN("",TRUE,IF(ISNUMBER(MID(LEFT(MID(VLOOKUP(A1096,Sheet1!A:Z,12,FALSE),2,99),FIND(")",VLOOKUP(A1096,Sheet1!A:Z,12,FALSE))-2),ROW($1:$20),1)+0),MID(LEFT(MID(VLOOKUP(A1096,Sheet1!A:Z,12,FALSE),2,99),FIND(")",VLOOKUP(A1096,Sheet1!A:Z,12,FALSE))-2),ROW($1:$20),1),""))} -> 3 | E1096: =IF(ISNUMBER(SEARCH("Minimum", VLOOKUP(A1096, Sheet1!A:Z, 12, FALSE))), TRUE, FALSE) -> TRUE | F1096: =QUOTIENT(B1096, C1096) -> 0 | G1096: =VALUE(VLOOKUP(A1096, Sheet1!A:Z, 11, FALSE))>=10 -> TRUE | H1096: =VLOOKUP(A1096, Sheet1!A:Z, 11, FALSE) -> 25.80 | I1096: =VLOOKUP(A1096, Sheet1!A:Z, 13, FALSE) -> 13.30 | J1096: =IF(E1096, I1096, IF(C1096<>D1096,I1096,H1096)) -> 13.30 | K1096: =(J1096+20%)*2.8 -> 37.8 | L1096: =VLOOKUP(A1096, Sheet1!A:Z, 5, FALSE) -> 048893217709 | M1096: =LEFT(L1096, LEN(L1096)-1) -> 04889321770 | N1096: =(3000000000000+M1096) -> 3004889321770 | O1096: =(5000000000000+M1096) -> 5004889321770 | P1096: {=N1096 & MOD(10 - MOD(SUMPRODUCT(MID(N1096, ROW(INDIRECT("1:" & LEN(N1096))), 1) * IF(MOD(ROW(INDIRECT("1:" & LEN(N1096))), 2) = 0, 1, 3)), 10), 10)} -> 30048893217700
A1097: 4319251 | B1097: =VLOOKUP(A1097, Sheet1!A:Z, 2, FALSE) -> 3 | D1097: {=--_xlfn.TEXTJOIN("",TRUE,IF(ISNUMBER(MID(LEFT(MID(VLOOKUP(A1097,Sheet1!A:Z,12,FALSE),2,99),FIND(")",VLOOKUP(A1097,Sheet1!A:Z,12,FALSE))-2),ROW($1:$20),1)+0),MID(LEFT(MID(VLOOKUP(A1097,Sheet1!A:Z,12,FALSE),2,99),FIND(")",VLOOKUP(A1097,Sheet1!A:Z,12,FALSE))-2),ROW($1:$20),1),""))} -> 4 | E1097: =IF(ISNUMBER(SEARCH("Minimum", VLOOKUP(A1097, Sheet1!A:Z, 12, FALSE))), TRUE, FALSE) -> FALSE | F1097: =QUOTIENT(B1097, C1097) -> #DIV/0! | G1097: =VALUE(VLOOKUP(A1097, Sheet1!A:Z, 11, FALSE))>=10 -> TRUE | H1097: =VLOOKUP(A1097, Sheet1!A:Z, 11, FALSE) -> 28.20 | I1097: =VLOOKUP(A1097, Sheet1!A:Z, 13, FALSE) -> 25.05 | J1097: =IF(E1097, I1097, IF(C1097<>D1097,I1097,H1097)) -> 25.05 | K1097: =(J1097+20%)*2.8 -> 70.7 | L1097: =VLOOKUP(A1097, Sheet1!A:Z, 5, FALSE) -> 048893550554 | M1097: =LEFT(L1097, LEN(L1097)-1) -> 04889355055 | N1097: =(3000000000000+M1097) -> 3004889355055 | O1097: =(5000000000000+M1097) -> 5004889355055 | P1097: {=N1097 & MOD(10 - MOD(SUMPRODUCT(MID(N1097, ROW(INDIRECT("1:" & LEN(N1097))), 1) * IF(MOD(ROW(INDIRECT("1:" & LEN(N1097))), 2) = 0, 1, 3)), 10), 10)} -> 30048893550555
A1098: 4401613 | B1098: =VLOOKUP(A1098, Sheet1!A:Z, 2, FALSE) -> 3 | C1098: 6 | D1098: {=--_xlfn.TEXTJOIN("",TRUE,IF(ISNUMBER(MID(LEFT(MID(VLOOKUP(A1098,Sheet1!A:Z,12,FALSE),2,99),FIND(")",VLOOKUP(A1098,Sheet1!A:Z,12,FALSE))-2),ROW($1:$20),1)+0),MID(LEFT(MID(VLOOKUP(A1098,Sheet1!A:Z,12,FALSE),2,99),FIND(")",VLOOKUP(A1098,Sheet1!A:Z,12,FALSE))-2),ROW($1:$20),1),""))} -> 3 | E1098: =IF(ISNUMBER(SEARCH("Minimum", VLOOKUP(A1098, Sheet1!A:Z, 12, FALSE))), TRUE, FALSE) -> TRUE | F1098: =QUOTIENT(B1098, C1098) -> 0 | G1098: =VALUE(VLOOKUP(A1098, Sheet1!A:Z, 11, FALSE))>=10 -> TRUE | H1098: =VLOOKUP(A1098, Sheet1!A:Z, 11, FALSE) -> 22.00 | I1098: =VLOOKUP(A1098, Sheet1!A:Z, 13, FALSE) -> 11.85 | J1098: =IF(E1098, I1098, IF(C1098<>D1098,I1098,H1098)) -> 11.85 | K1098: =(J1098+20%)*2.8 -> 33.74 | L1098: =VLOOKUP(A1098, Sheet1!A:Z, 5, FALSE) -> 048893996239 | M1098: =LEFT(L1098, LEN(L1098)-1) -> 04889399623 | N1098: =(3000000000000+M1098) -> 3004889399623 | O1098: =(5000000000000+M1098) -> 5004889399623 | P1098: {=N1098 & MOD(10 - MOD(SUMPRODUCT(MID(N1098, ROW(INDIRECT("1:" & LEN(N1098))), 1) * IF(MOD(ROW(INDIRECT("1:" & LEN(N1098))), 2) = 0, 1, 3)), 10), 10)} -> 30048893996230
A1099: 4401637 | B1099: =VLOOKUP(A1099, Sheet1!A:Z, 2, FALSE) -> 3 | C1099: 4 | D1099: {=--_xlfn.TEXTJOIN("",TRUE,IF(ISNUMBER(MID(LEFT(MID(VLOOKUP(A1099,Sheet1!A:Z,12,FALSE),2,99),FIND(")",VLOOKUP(A1099,Sheet1!A:Z,12,FALSE))-2),ROW($1:$20),1)+0),MID(LEFT(MID(VLOOKUP(A1099,Sheet1!A:Z,12,FALSE),2,99),FIND(")",VLOOKUP(A1099,Sheet1!A:Z,12,FALSE))-2),ROW($1:$20),1),""))} -> 2 | E1099: =IF(ISNUMBER(SEARCH("Minimum", VLOOKUP(A1099, Sheet1!A:Z, 12, FALSE))), TRUE, FALSE) -> TRUE | F1099: =QUOTIENT(B1099, C1099) -> 0 | G1099: =VALUE(VLOOKUP(A1099, Sheet1!A:Z, 11, FALSE))>=10 -> TRUE | H1099: =VLOOKUP(A1099, Sheet1!A:Z, 11, FALSE) -> 77.00 | I1099: =VLOOKUP(A1099, Sheet1!A:Z, 13, FALSE) -> 41.40 | J1099: =IF(E1099, I1099, IF(C1099<>D1099,I1099,H1099)) -> 41.40 | K1099: =(J1099+20%)*2.8 -> 116.48 | L1099: =VLOOKUP(A1099, Sheet1!A:Z, 5, FALSE) -> 048893996123 | M1099: =LEFT(L1099, LEN(L1099)-1) -> 04889399612 | N1099: =(3000000000000+M1099) -> 3004889399612 | O1099: =(5000000000000+M1099) -> 5004889399612 | P1099: {=N1099 & MOD(10 - MOD(SUMPRODUCT(MID(N1099, ROW(INDIRECT("1:" & LEN(N1099))), 1) * IF(MOD(ROW(INDIRECT("1:" & LEN(N1099))), 2) = 0, 1, 3)), 10), 10)} -> 30048893996124
A1100: 4415583 | B1100: =VLOOKUP(A1100, Sheet1!A:Z, 2, FALSE) -> 3 | C1100: 3 | D1100: {=--_xlfn.TEXTJOIN("",TRUE,IF(ISNUMBER(MID(LEFT(MID(VLOOKUP(A1100,Sheet1!A:Z,12,FALSE),2,99),FIND(")",VLOOKUP(A1100,Sheet1!A:Z,12,FALSE))-2),ROW($1:$20),1)+0),MID(LEFT(MID(VLOOKUP(A1100,Sheet1!A:Z,12,FALSE),2,99),FIND(")",VLOOKUP(A1100,Sheet1!A:Z,12,FALSE))-2),ROW($1:$20),1),""))} -> 3 | E1100: =IF(ISNUMBER(SEARCH("Minimum", VLOOKUP(A1100, Sheet1!A:Z, 12, FALSE))), TRUE, FALSE) -> FALSE | F1100: =QUOTIENT(B1100, C1100) -> 1 | G1100: =VALUE(VLOOKUP(A1100, Sheet1!A:Z, 11, FALSE))>=10 -> TRUE | H1100: =VLOOKUP(A1100, Sheet1!A:Z, 11, FALSE) -> 39.40 | I1100: =VLOOKUP(A1100, Sheet1!A:Z, 13, FALSE) -> 34.95 | J1100: =IF(E1100, I1100, IF(C1100<>D1100,I1100,H1100)) -> 34.95 | K1100: =(J1100+20%)*2.8 -> 98.42 | L1100: =VLOOKUP(A1100, Sheet1!A:Z, 5, FALSE) -> 048893499082 | M1100: =LEFT(L1100, LEN(L1100)-1) -> 04889349908 | N1100: =(3000000000000+M1100) -> 3004889349908 | O1100: =(5000000000000+M1100) -> 5004889349908 | P1100: {=N1100 & MOD(10 - MOD(SUMPRODUCT(MID(N1100, ROW(INDIRECT("1:" & LEN(N1100))), 1) * IF(MOD(ROW(INDIRECT("1:" & LEN(N1100))), 2) = 0, 1, 3)), 10), 10)} -> 30048893499083
A1101: 4419630 | B1101: =VLOOKUP(A1101, Sheet1!A:Z, 2, FALSE) -> 3 | C1101: 4 | D1101: {=--_xlfn.TEXTJOIN("",TRUE,IF(ISNUMBER(MID(LEFT(MID(VLOOKUP(A1101,Sheet1!A:Z,12,FALSE),2,99),FIND(")",VLOOKUP(A1101,Sheet1!A:Z,12,FALSE))-2),ROW($1:$20),1)+0),MID(LEFT(MID(VLOOKUP(A1101,Sheet1!A:Z,12,FALSE),2,99),FIND(")",VLOOKUP(A1101,Sheet1!A:Z,12,FALSE))-2),ROW($1:$20),1),""))} -> 2 | E1101: =IF(ISNUMBER(SEARCH("Minimum", VLOOKUP(A1101, Sheet1!A:Z, 12, FALSE))), TRUE, FALSE) -> TRUE | F1101: =QUOTIENT(B1101, C1101) -> 0 | G1101: =VALUE(VLOOKUP(A1101, Sheet1!A:Z, 11, FALSE))>=10 -> TRUE | H1101: =VLOOKUP(A1101, Sheet1!A:Z, 11, FALSE) -> 41.50 | I1101: =VLOOKUP(A1101, Sheet1!A:Z, 13, FALSE) -> 22.20 | J1101: =IF(E1101, I1101, IF(C1101<>D1101,I1101,H1101)) -> 22.20 | K1101: =(J1101+20%)*2.8 -> 62.72 | L1101: =VLOOKUP(A1101, Sheet1!A:Z, 5, FALSE) -> 048893495152 | M1101: =LEFT(L1101, LEN(L1101)-1) -> 04889349515 | N1101: =(3000000000000+M1101) -> 3004889349515 | O1101: =(5000000000000+M1101) -> 5004889349515 | P1101: {=N1101 & MOD(10 - MOD(SUMPRODUCT(MID(N1101, ROW(INDIRECT("1:" & LEN(N1101))), 1) * IF(MOD(ROW(INDIRECT("1:" & LEN(N1101))), 2) = 0, 1, 3)), 10), 10)} -> 30048893495153
A1102: 4510368 | B1102: =VLOOKUP(A1102, Sheet1!A:Z, 2, FALSE) -> 3 | C1102: 3 | D1102: {=--_xlfn.TEXTJOIN("",TRUE,IF(ISNUMBER(MID(LEFT(MID(VLOOKUP(A1102,Sheet1!A:Z,12,FALSE),2,99),FIND(")",VLOOKUP(A1102,Sheet1!A:Z,12,FALSE))-2),ROW($1:$20),1)+0),MID(LEFT(MID(VLOOKUP(A1102,Sheet1!A:Z,12,FALSE),2,99),FIND(")",VLOOKUP(A1102,Sheet1!A:Z,12,FALSE))-2),ROW($1:$20),1),""))} -> 3 | E1102: =IF(ISNUMBER(SEARCH("Minimum", VLOOKUP(A1102, Sheet1!A:Z, 12, FALSE))), TRUE, FALSE) -> FALSE | F1102: =QUOTIENT(B1102, C1102) -> 1 | G1102: =VALUE(VLOOKUP(A1102, Sheet1!A:Z, 11, FALSE))>=10 -> TRUE | H1102: =VLOOKUP(A1102, Sheet1!A:Z, 11, FALSE) -> 42.30 | I1102: =VLOOKUP(A1102, Sheet1!A:Z, 13, FALSE) -> 37.25 | J1102: =IF(E1102, I1102, IF(C1102<>D1102,I1102,H1102)) -> 37.25 | K1102: =(J1102+20%)*2.8 -> 104.86 | L1102: =VLOOKUP(A1102, Sheet1!A:Z, 5, FALSE) -> 048893959890 | M1102: =LEFT(L1102, LEN(L1102)-1) -> 04889395989 | N1102: =(3000000000000+M1102) -> 3004889395989 | O1102: =(5000000000000+M1102) -> 5004889395989 | P1102: {=N1102 & MOD(10 - MOD(SUMPRODUCT(MID(N1102, ROW(INDIRECT("1:" & LEN(N1102))), 1) * IF(MOD(ROW(INDIRECT("1:" & LEN(N1102))), 2) = 0, 1, 3)), 10), 10)} -> 30048893959891
A1103: 4511646 | B1103: =VLOOKUP(A1103, Sheet1!A:Z, 2, FALSE) -> 3 | C1103: 3 | D1103: {=--_xlfn.TEXTJOIN("",TRUE,IF(ISNUMBER(MID(LEFT(MID(VLOOKUP(A1103,Sheet1!A:Z,12,FALSE),2,99),FIND(")",VLOOKUP(A1103,Sheet1!A:Z,12,FALSE))-2),ROW($1:$20),1)+0),MID(LEFT(MID(VLOOKUP(A1103,Sheet1!A:Z,12,FALSE),2,99),FIND(")",VLOOKUP(A1103,Sheet1!A:Z,12,FALSE))-2),ROW($1:$20),1),""))} -> 3 | E1103: =IF(ISNUMBER(SEARCH("Minimum", VLOOKUP(A1103, Sheet1!A:Z, 12, FALSE))), TRUE, FALSE) -> FALSE | F1103: =QUOTIENT(B1103, C1103) -> 1 | G1103: =VALUE(VLOOKUP(A1103, Sheet1!A:Z, 11, FALSE))>=10 -> TRUE | H1103: =VLOOKUP(A1103, Sheet1!A:Z, 11, FALSE) -> 29.30 | I1103: =VLOOKUP(A1103, Sheet1!A:Z, 13, FALSE) -> 26.10 | J1103: =IF(E1103, I1103, IF(C1103<>D1103,I1103,H1103)) -> 26.10 | K1103: =(J1103+20%)*2.8 -> 73.64 | L1103: =VLOOKUP(A1103, Sheet1!A:Z, 5, FALSE) -> 048893958008 | M1103: =LEFT(L1103, LEN(L1103)-1) -> 04889395800 | N1103: =(3000000000000+M1103) -> 3004889395800 | O1103: =(5000000000000+M1103) -> 5004889395800 | P1103: {=N1103 & MOD(10 - MOD(SUMPRODUCT(MID(N1103, ROW(INDIRECT("1:" & LEN(N1103))), 1) * IF(MOD(ROW(INDIRECT("1:" & LEN(N1103))), 2) = 0, 1, 3)), 10), 10)} -> 30048893958009
A1104: 4519212 | B1104: =VLOOKUP(A1104, Sheet1!A:Z, 2, FALSE) -> 3 | C1104: 3 | D1104: {=--_xlfn.TEXTJOIN("",TRUE,IF(ISNUMBER(MID(LEFT(MID(VLOOKUP(A1104,Sheet1!A:Z,12,FALSE),2,99),FIND(")",VLOOKUP(A1104,Sheet1!A:Z,12,FALSE))-2),ROW($1:$20),1)+0),MID(LEFT(MID(VLOOKUP(A1104,Sheet1!A:Z,12,FALSE),2,99),FIND(")",VLOOKUP(A1104,Sheet1!A:Z,12,FALSE))-2),ROW($1:$20),1),""))} -> 3 | E1104: =IF(ISNUMBER(SEARCH("Minimum", VLOOKUP(A1104, Sheet1!A:Z, 12, FALSE))), TRUE, FALSE) -> FALSE | F1104: =QUOTIENT(B1104, C1104) -> 1 | G1104: =VALUE(VLOOKUP(A1104, Sheet1!A:Z, 11, FALSE))>=10 -> TRUE | H1104: =VLOOKUP(A1104, Sheet1!A:Z, 11, FALSE) -> 36.00 | I1104: =VLOOKUP(A1104, Sheet1!A:Z, 13, FALSE) -> 31.95 | J1104: =IF(E1104, I1104, IF(C1104<>D1104,I1104,H1104)) -> 31.95 | K1104: =(J1104+20%)*2.8 -> 90.02 | L1104: =VLOOKUP(A1104, Sheet1!A:Z, 5, FALSE) -> 048893952181 | M1104: =LEFT(L1104, LEN(L1104)-1) -> 04889395218 | N1104: =(3000000000000+M1104) -> 3004889395218 | O1104: =(5000000000000+M1104) -> 5004889395218 | P1104: {=N1104 & MOD(10 - MOD(SUMPRODUCT(MID(N1104, ROW(INDIRECT("1:" & LEN(N1104))), 1) * IF(MOD(ROW(INDIRECT("1:" & LEN(N1104))), 2) = 0, 1, 3)), 10), 10)} -> 30048893952182
A1105: 4524989 | B1105: =VLOOKUP(A1105, Sheet1!A:Z, 2, FALSE) -> 3 | C1105: 3 | D1105: {=--_xlfn.TEXTJOIN("",TRUE,IF(ISNUMBER(MID(LEFT(MID(VLOOKUP(A1105,Sheet1!A:Z,12,FALSE),2,99),FIND(")",VLOOKUP(A1105,Sheet1!A:Z,12,FALSE))-2),ROW($1:$20),1)+0),MID(LEFT(MID(VLOOKUP(A1105,Sheet1!A:Z,12,FALSE),2,99),FIND(")",VLOOKUP(A1105,Sheet1!A:Z,12,FALSE))-2),ROW($1:$20),1),""))} -> 3 | E1105: =IF(ISNUMBER(SEARCH("Minimum", VLOOKUP(A1105, Sheet1!A:Z, 12, FALSE))), TRUE, FALSE) -> FALSE | F1105: =QUOTIENT(B1105, C1105) -> 1 | G1105: =VALUE(VLOOKUP(A1105, Sheet1!A:Z, 11, FALSE))>=10 -> TRUE | H1105: =VLOOKUP(A1105, Sheet1!A:Z, 11, FALSE) -> 39.60 | I1105: =VLOOKUP(A1105, Sheet1!A:Z, 13, FALSE) -> 35.05 | J1105: =IF(E1105, I1105, IF(C1105<>D1105,I1105,H1105)) -> 35.05 | K1105: =(J1105+20%)*2.8 -> 98.7 | L1105: =VLOOKUP(A1105, Sheet1!A:Z, 5, FALSE) -> 048893435554 | M1105: =LEFT(L1105, LEN(L1105)-1) -> 04889343555 | N1105: =(3000000000000+M1105) -> 3004889343555 | O1105: =(5000000000000+M1105) -> 5004889343555 | P1105: {=N1105 & MOD(10 - MOD(SUMPRODUCT(MID(N1105, ROW(INDIRECT("1:" & LEN(N1105))), 1) * IF(MOD(ROW(INDIRECT("1:" & LEN(N1105))), 2) = 0, 1, 3)), 10), 10)} -> 30048893435555
A1106: 4557381 | B1106: =VLOOKUP(A1106, Sheet1!A:Z, 2, FALSE) -> 3 | C1106: 3 | D1106: {=--_xlfn.TEXTJOIN("",TRUE,IF(ISNUMBER(MID(LEFT(MID(VLOOKUP(A1106,Sheet1!A:Z,12,FALSE),2,99),FIND(")",VLOOKUP(A1106,Sheet1!A:Z,12,FALSE))-2),ROW($1:$20),1)+0),MID(LEFT(MID(VLOOKUP(A1106,Sheet1!A:Z,12,FALSE),2,99),FIND(")",VLOOKUP(A1106,Sheet1!A:Z,12,FALSE))-2),ROW($1:$20),1),""))} -> 3 | E1106: =IF(ISNUMBER(SEARCH("Minimum", VLOOKUP(A1106, Sheet1!A:Z, 12, FALSE))), TRUE, FALSE) -> FALSE | F1106: =QUOTIENT(B1106, C1106) -> 1 | G1106: =VALUE(VLOOKUP(A1106, Sheet1!A:Z, 11, FALSE))>=10 -> TRUE | H1106: =VLOOKUP(A1106, Sheet1!A:Z, 11, FALSE) -> 23.95 | I1106: =VLOOKUP(A1106, Sheet1!A:Z, 13, FALSE) -> 21.10 | J1106: =IF(E1106, I1106, IF(C1106<>D1106,I1106,H1106)) -> 21.10 | K1106: =(J1106+20%)*2.8 -> 59.64 | L1106: =VLOOKUP(A1106, Sheet1!A:Z, 5, FALSE) -> 048893430221 | M1106: =LEFT(L1106, LEN(L1106)-1) -> 04889343022 | N1106: =(3000000000000+M1106) -> 3004889343022 | O1106: =(5000000000000+M1106) -> 5004889343022 | P1106: {=N1106 & MOD(10 - MOD(SUMPRODUCT(MID(N1106, ROW(INDIRECT("1:" & LEN(N1106))), 1) * IF(MOD(ROW(INDIRECT("1:" & LEN(N1106))), 2) = 0, 1, 3)), 10), 10)} -> 30048893430222
A1107: 4559179 | B1107: =VLOOKUP(A1107, Sheet1!A:Z, 2, FALSE) -> 3 | C1107: 2 | D1107: {=--_xlfn.TEXTJOIN("",TRUE,IF(ISNUMBER(MID(LEFT(MID(VLOOKUP(A1107,Sheet1!A:Z,12,FALSE),2,99),FIND(")",VLOOKUP(A1107,Sheet1!A:Z,12,FALSE))-2),ROW($1:$20),1)+0),MID(LEFT(MID(VLOOKUP(A1107,Sheet1!A:Z,12,FALSE),2,99),FIND(")",VLOOKUP(A1107,Sheet1!A:Z,12,FALSE))-2),ROW($1:$20),1),""))} -> 2 | E1107: =IF(ISNUMBER(SEARCH("Minimum", VLOOKUP(A1107, Sheet1!A:Z, 12, FALSE))), TRUE, FALSE) -> FALSE | F1107: =QUOTIENT(B1107, C1107) -> 1 | G1107: =VALUE(VLOOKUP(A1107, Sheet1!A:Z, 11, FALSE))>=10 -> TRUE | H1107: =VLOOKUP(A1107, Sheet1!A:Z, 11, FALSE) -> 42.40 | I1107: =VLOOKUP(A1107, Sheet1!A:Z, 13, FALSE) -> 37.50 | J1107: =IF(E1107, I1107, IF(C1107<>D1107,I1107,H1107)) -> 37.50 | K1107: =(J1107+20%)*2.8 -> 105.56 | L1107: =VLOOKUP(A1107, Sheet1!A:Z, 5, FALSE) -> 048893940409 | M1107: =LEFT(L1107, LEN(L1107)-1) -> 04889394040 | N1107: =(3000000000000+M1107) -> 3004889394040 | O1107: =(5000000000000+M1107) -> 5004889394040 | P1107: {=N1107 & MOD(10 - MOD(SUMPRODUCT(MID(N1107, ROW(INDIRECT("1:" & LEN(N1107))), 1) * IF(MOD(ROW(INDIRECT("1:" & LEN(N1107))), 2) = 0, 1, 3)), 10), 10)} -> 30048893940400
A1108: T4252035 | B1108: =VLOOKUP(A1108, Sheet1!A:Z, 2, FALSE) -> 3 | C1108: 4 | D1108: {=--_xlfn.TEXTJOIN("",TRUE,IF(ISNUMBER(MID(LEFT(MID(VLOOKUP(A1108,Sheet1!A:Z,12,FALSE),2,99),FIND(")",VLOOKUP(A1108,Sheet1!A:Z,12,FALSE))-2),ROW($1:$20),1)+0),MID(LEFT(MID(VLOOKUP(A1108,Sheet1!A:Z,12,FALSE),2,99),FIND(")",VLOOKUP(A1108,Sheet1!A:Z,12,FALSE))-2),ROW($1:$20),1),""))} -> 1 | E1108: =IF(ISNUMBER(SEARCH("Minimum", VLOOKUP(A1108, Sheet1!A:Z, 12, FALSE))), TRUE, FALSE) -> TRUE | F1108: =QUOTIENT(B1108, C1108) -> 0 | G1108: =VALUE(VLOOKUP(A1108, Sheet1!A:Z, 11, FALSE))>=10 -> TRUE | H1108: =VLOOKUP(A1108, Sheet1!A:Z, 11, FALSE) -> 485.00 | I1108: =VLOOKUP(A1108, Sheet1!A:Z, 13, FALSE) -> 261.00 | J1108: =IF(E1108, I1108, IF(C1108<>D1108,I1108,H1108)) -> 261.00 | K1108: =(J1108+20%)*2.8 -> 731.36 | L1108: =VLOOKUP(A1108, Sheet1!A:Z, 5, FALSE) -> 048893753719 | M1108: =LEFT(L1108, LEN(L1108)-1) -> 04889375371 | N1108: =(3000000000000+M1108) -> 3004889375371 | O1108: =(5000000000000+M1108) -> 5004889375371 | P1108: {=N1108 & MOD(10 - MOD(SUMPRODUCT(MID(N1108, ROW(INDIRECT("1:" & LEN(N1108))), 1) * IF(MOD(ROW(INDIRECT("1:" & LEN(N1108))), 2) = 0, 1, 3)), 10), 10)} -> 30048893753710
A1109: 3817594 | B1109: =VLOOKUP(A1109, Sheet1!A:Z, 2, FALSE) -> 2 | C1109: 2 | D1109: {=--_xlfn.TEXTJOIN("",TRUE,IF(ISNUMBER(MID(LEFT(MID(VLOOKUP(A1109,Sheet1!A:Z,12,FALSE),2,99),FIND(")",VLOOKUP(A1109,Sheet1!A:Z,12,FALSE))-2),ROW($1:$20),1)+0),MID(LEFT(MID(VLOOKUP(A1109,Sheet1!A:Z,12,FALSE),2,99),FIND(")",VLOOKUP(A1109,Sheet1!A:Z,12,FALSE))-2),ROW($1:$20),1),""))} -> 2 | E1109: =IF(ISNUMBER(SEARCH("Minimum", VLOOKUP(A1109, Sheet1!A:Z, 12, FALSE))), TRUE, FALSE) -> FALSE | F1109: =QUOTIENT(B1109, C1109) -> 1 | G1109: =VALUE(VLOOKUP(A1109, Sheet1!A:Z, 11, FALSE))>=10 -> TRUE | H1109: =VLOOKUP(A1109, Sheet1!A:Z, 11, FALSE) -> 29.50 | I1109: =VLOOKUP(A1109, Sheet1!A:Z, 13, FALSE) -> 24.90 | J1109: =IF(E1109, I1109, IF(C1109<>D1109,I1109,H1109)) -> 24.90 | K1109: =(J1109+20%)*2.8 -> 70.28 | L1109: =VLOOKUP(A1109, Sheet1!A:Z, 5, FALSE) -> 048893222673 | M1109: =LEFT(L1109, LEN(L1109)-1) -> 04889322267 | N1109: =(3000000000000+M1109) -> 3004889322267 | O1109: =(5000000000000+M1109) -> 5004889322267 | P1109: {=N1109 & MOD(10 - MOD(SUMPRODUCT(MID(N1109, ROW(INDIRECT("1:" & LEN(N1109))), 1) * IF(MOD(ROW(INDIRECT("1:" & LEN(N1109))), 2) = 0, 1, 3)), 10), 10)} -> 30048893222674
A1110: 3919039 | B1110: =VLOOKUP(A1110, Sheet1!A:Z, 2, FALSE) -> 2 | D1110: {=--_xlfn.TEXTJOIN("",TRUE,IF(ISNUMBER(MID(LEFT(MID(VLOOKUP(A1110,Sheet1!A:Z,12,FALSE),2,99),FIND(")",VLOOKUP(A1110,Sheet1!A:Z,12,FALSE))-2),ROW($1:$20),1)+0),MID(LEFT(MID(VLOOKUP(A1110,Sheet1!A:Z,12,FALSE),2,99),FIND(")",VLOOKUP(A1110,Sheet1!A:Z,12,FALSE))-2),ROW($1:$20),1),""))} -> 4 | E1110: =IF(ISNUMBER(SEARCH("Minimum", VLOOKUP(A1110, Sheet1!A:Z, 12, FALSE))), TRUE, FALSE) -> FALSE | F1110: =QUOTIENT(B1110, C1110) -> #DIV/0! | G1110: =VALUE(VLOOKUP(A1110, Sheet1!A:Z, 11, FALSE))>=10 -> TRUE | H1110: =VLOOKUP(A1110, Sheet1!A:Z, 11, FALSE) -> 26.90 | I1110: =VLOOKUP(A1110, Sheet1!A:Z, 13, FALSE) -> 24.30 | J1110: =IF(E1110, I1110, IF(C1110<>D1110,I1110,H1110)) -> 24.30 | K1110: =(J1110+20%)*2.8 -> 68.6 | L1110: =VLOOKUP(A1110, Sheet1!A:Z, 5, FALSE) -> 048893079567 | M1110: =LEFT(L1110, LEN(L1110)-1) -> 04889307956 | N1110: =(3000000000000+M1110) -> 3004889307956 | O1110: =(5000000000000+M1110) -> 5004889307956 | P1110: {=N1110 & MOD(10 - MOD(SUMPRODUCT(MID(N1110, ROW(INDIRECT("1:" & LEN(N1110))), 1) * IF(MOD(ROW(INDIRECT("1:" & LEN(N1110))), 2) = 0, 1, 3)), 10), 10)} -> 30048893079568
A1111: 4228006 | B1111: =VLOOKUP(A1111, Sheet1!A:Z, 2, FALSE) -> 2 | C1111: 4 | D1111: {=--_xlfn.TEXTJOIN("",TRUE,IF(ISNUMBER(MID(LEFT(MID(VLOOKUP(A1111,Sheet1!A:Z,12,FALSE),2,99),FIND(")",VLOOKUP(A1111,Sheet1!A:Z,12,FALSE))-2),ROW($1:$20),1)+0),MID(LEFT(MID(VLOOKUP(A1111,Sheet1!A:Z,12,FALSE),2,99),FIND(")",VLOOKUP(A1111,Sheet1!A:Z,12,FALSE))-2),ROW($1:$20),1),""))} -> 2 | E1111: =IF(ISNUMBER(SEARCH("Minimum", VLOOKUP(A1111, Sheet1!A:Z, 12, FALSE))), TRUE, FALSE) -> TRUE | F1111: =QUOTIENT(B1111, C1111) -> 0 | G1111: =VALUE(VLOOKUP(A1111, Sheet1!A:Z, 11, FALSE))>=10 -> TRUE | H1111: =VLOOKUP(A1111, Sheet1!A:Z, 11, FALSE) -> 84.00 | I1111: =VLOOKUP(A1111, Sheet1!A:Z, 13, FALSE) -> 44.70 | J1111: =IF(E1111, I1111, IF(C1111<>D1111,I1111,H1111)) -> 44.70 | K1111: =(J1111+20%)*2.8 -> 125.72 | L1111: =VLOOKUP(A1111, Sheet1!A:Z, 5, FALSE) -> 048893147082 | M1111: =LEFT(L1111, LEN(L1111)-1) -> 04889314708 | N1111: =(3000000000000+M1111) -> 3004889314708 | O1111: =(5000000000000+M1111) -> 5004889314708 | P1111: {=N1111 & MOD(10 - MOD(SUMPRODUCT(MID(N1111, ROW(INDIRECT("1:" & LEN(N1111))), 1) * IF(MOD(ROW(INDIRECT("1:" & LEN(N1111))), 2) = 0, 1, 3)), 10), 10)} -> 30048893147083
A1112: 4300758 | B1112: =VLOOKUP(A1112, Sheet1!A:Z, 2, FALSE) -> 2 | D1112: {=--_xlfn.TEXTJOIN("",TRUE,IF(ISNUMBER(MID(LEFT(MID(VLOOKUP(A1112,Sheet1!A:Z,12,FALSE),2,99),FIND(")",VLOOKUP(A1112,Sheet1!A:Z,12,FALSE))-2),ROW($1:$20),1)+0),MID(LEFT(MID(VLOOKUP(A1112,Sheet1!A:Z,12,FALSE),2,99),FIND(")",VLOOKUP(A1112,Sheet1!A:Z,12,FALSE))-2),ROW($1:$20),1),""))} -> 4 | E1112: =IF(ISNUMBER(SEARCH("Minimum", VLOOKUP(A1112, Sheet1!A:Z, 12, FALSE))), TRUE, FALSE) -> FALSE | F1112: =QUOTIENT(B1112, C1112) -> #DIV/0! | G1112: =VALUE(VLOOKUP(A1112, Sheet1!A:Z, 11, FALSE))>=10 -> TRUE | H1112: =VLOOKUP(A1112, Sheet1!A:Z, 11, FALSE) -> 25.05 | I1112: =VLOOKUP(A1112, Sheet1!A:Z, 13, FALSE) -> 22.15 | J1112: =IF(E1112, I1112, IF(C1112<>D1112,I1112,H1112)) -> 22.15 | K1112: =(J1112+20%)*2.8 -> 62.58 | L1112: =VLOOKUP(A1112, Sheet1!A:Z, 5, FALSE) -> 048893083922 | M1112: =LEFT(L1112, LEN(L1112)-1) -> 04889308392 | N1112: =(3000000000000+M1112) -> 3004889308392 | O1112: =(5000000000000+M1112) -> 5004889308392 | P1112: {=N1112 & MOD(10 - MOD(SUMPRODUCT(MID(N1112, ROW(INDIRECT("1:" & LEN(N1112))), 1) * IF(MOD(ROW(INDIRECT("1:" & LEN(N1112))), 2) = 0, 1, 3)), 10), 10)} -> 30048893083923
A1113: 4411609 | B1113: =VLOOKUP(A1113, Sheet1!A:Z, 2, FALSE) -> 2 | C1113: 4 | D1113: {=--_xlfn.TEXTJOIN("",TRUE,IF(ISNUMBER(MID(LEFT(MID(VLOOKUP(A1113,Sheet1!A:Z,12,FALSE),2,99),FIND(")",VLOOKUP(A1113,Sheet1!A:Z,12,FALSE))-2),ROW($1:$20),1)+0),MID(LEFT(MID(VLOOKUP(A1113,Sheet1!A:Z,12,FALSE),2,99),FIND(")",VLOOKUP(A1113,Sheet1!A:Z,12,FALSE))-2),ROW($1:$20),1),""))} -> 2 | E1113: =IF(ISNUMBER(SEARCH("Minimum", VLOOKUP(A1113, Sheet1!A:Z, 12, FALSE))), TRUE, FALSE) -> TRUE | F1113: =QUOTIENT(B1113, C1113) -> 0 | G1113: =VALUE(VLOOKUP(A1113, Sheet1!A:Z, 11, FALSE))>=10 -> TRUE | H1113: =VLOOKUP(A1113, Sheet1!A:Z, 11, FALSE) -> 50.00 | I1113: =VLOOKUP(A1113, Sheet1!A:Z, 13, FALSE) -> 27.00 | J1113: =IF(E1113, I1113, IF(C1113<>D1113,I1113,H1113)) -> 27.00 | K1113: =(J1113+20%)*2.8 -> 76.16 | L1113: =VLOOKUP(A1113, Sheet1!A:Z, 5, FALSE) -> 048893995218 | M1113: =LEFT(L1113, LEN(L1113)-1) -> 04889399521 | N1113: =(3000000000000+M1113) -> 3004889399521 | O1113: =(5000000000000+M1113) -> 5004889399521 | P1113: {=N1113 & MOD(10 - MOD(SUMPRODUCT(MID(N1113, ROW(INDIRECT("1:" & LEN(N1113))), 1) * IF(MOD(ROW(INDIRECT("1:" & LEN(N1113))), 2) = 0, 1, 3)), 10), 10)} -> 30048893995219
A1114: 4416230 | B1114: =VLOOKUP(A1114, Sheet1!A:Z, 2, FALSE) -> 2 | C1114: 2 | D1114: {=--_xlfn.TEXTJOIN("",TRUE,IF(ISNUMBER(MID(LEFT(MID(VLOOKUP(A1114,Sheet1!A:Z,12,FALSE),2,99),FIND(")",VLOOKUP(A1114,Sheet1!A:Z,12,FALSE))-2),ROW($1:$20),1)+0),MID(LEFT(MID(VLOOKUP(A1114,Sheet1!A:Z,12,FALSE),2,99),FIND(")",VLOOKUP(A1114,Sheet1!A:Z,12,FALSE))-2),ROW($1:$20),1),""))} -> 2 | E1114: =IF(ISNUMBER(SEARCH("Minimum", VLOOKUP(A1114, Sheet1!A:Z, 12, FALSE))), TRUE, FALSE) -> FALSE | F1114: =QUOTIENT(B1114, C1114) -> 1 | G1114: =VALUE(VLOOKUP(A1114, Sheet1!A:Z, 11, FALSE))>=10 -> TRUE | H1114: =VLOOKUP(A1114, Sheet1!A:Z, 11, FALSE) -> 51.10 | I1114: =VLOOKUP(A1114, Sheet1!A:Z, 13, FALSE) -> 45.25 | J1114: =IF(E1114, I1114, IF(C1114<>D1114,I1114,H1114)) -> 45.25 | K1114: =(J1114+20%)*2.8 -> 127.26 | L1114: =VLOOKUP(A1114, Sheet1!A:Z, 5, FALSE) -> 048893994204 | M1114: =LEFT(L1114, LEN(L1114)-1) -> 04889399420 | N1114: =(3000000000000+M1114) -> 3004889399420 | O1114: =(5000000000000+M1114) -> 5004889399420 | P1114: {=N1114 & MOD(10 - MOD(SUMPRODUCT(MID(N1114, ROW(INDIRECT("1:" & LEN(N1114))), 1) * IF(MOD(ROW(INDIRECT("1:" & LEN(N1114))), 2) = 0, 1, 3)), 10), 10)} -> 30048893994205
A1115: 4419124 | B1115: =VLOOKUP(A1115, Sheet1!A:Z, 2, FALSE) -> 2 | C1115: 4 | D1115: {=--_xlfn.TEXTJOIN("",TRUE,IF(ISNUMBER(MID(LEFT(MID(VLOOKUP(A1115,Sheet1!A:Z,12,FALSE),2,99),FIND(")",VLOOKUP(A1115,Sheet1!A:Z,12,FALSE))-2),ROW($1:$20),1)+0),MID(LEFT(MID(VLOOKUP(A1115,Sheet1!A:Z,12,FALSE),2,99),FIND(")",VLOOKUP(A1115,Sheet1!A:Z,12,FALSE))-2),ROW($1:$20),1),""))} -> 2 | E1115: =IF(ISNUMBER(SEARCH("Minimum", VLOOKUP(A1115, Sheet1!A:Z, 12, FALSE))), TRUE, FALSE) -> TRUE | F1115: =QUOTIENT(B1115, C1115) -> 0 | G1115: =VALUE(VLOOKUP(A1115, Sheet1!A:Z, 11, FALSE))>=10 -> TRUE | H1115: =VLOOKUP(A1115, Sheet1!A:Z, 11, FALSE) -> 40.80 | I1115: =VLOOKUP(A1115, Sheet1!A:Z, 13, FALSE) -> 21.60 | J1115: =IF(E1115, I1115, IF(C1115<>D1115,I1115,H1115)) -> 21.60 | K1115: =(J1115+20%)*2.8 -> 61.04 | L1115: =VLOOKUP(A1115, Sheet1!A:Z, 5, FALSE) -> 048893993023 | M1115: =LEFT(L1115, LEN(L1115)-1) -> 04889399302 | N1115: =(3000000000000+M1115) -> 3004889399302 | O1115: =(5000000000000+M1115) -> 5004889399302 | P1115: {=N1115 & MOD(10 - MOD(SUMPRODUCT(MID(N1115, ROW(INDIRECT("1:" & LEN(N1115))), 1) * IF(MOD(ROW(INDIRECT("1:" & LEN(N1115))), 2) = 0, 1, 3)), 10), 10)} -> 30048893993024
A1116: 4421315 | B1116: =VLOOKUP(A1116, Sheet1!A:Z, 2, FALSE) -> 2 | C1116: 2 | D1116: {=--_xlfn.TEXTJOIN("",TRUE,IF(ISNUMBER(MID(LEFT(MID(VLOOKUP(A1116,Sheet1!A:Z,12,FALSE),2,99),FIND(")",VLOOKUP(A1116,Sheet1!A:Z,12,FALSE))-2),ROW($1:$20),1)+0),MID(LEFT(MID(VLOOKUP(A1116,Sheet1!A:Z,12,FALSE),2,99),FIND(")",VLOOKUP(A1116,Sheet1!A:Z,12,FALSE))-2),ROW($1:$20),1),""))} -> 2 | E1116: =IF(ISNUMBER(SEARCH("Minimum", VLOOKUP(A1116, Sheet1!A:Z, 12, FALSE))), TRUE, FALSE) -> FALSE | F1116: =QUOTIENT(B1116, C1116) -> 1 | G1116: =VALUE(VLOOKUP(A1116, Sheet1!A:Z, 11, FALSE))>=10 -> TRUE | H1116: =VLOOKUP(A1116, Sheet1!A:Z, 11, FALSE) -> 44.95 | I1116: =VLOOKUP(A1116, Sheet1!A:Z, 13, FALSE) -> 39.85 | J1116: =IF(E1116, I1116, IF(C1116<>D1116,I1116,H1116)) -> 39.85 | K1116: =(J1116+20%)*2.8 -> 112.14 | L1116: =VLOOKUP(A1116, Sheet1!A:Z, 5, FALSE) -> 048893493615 | M1116: =LEFT(L1116, LEN(L1116)-1) -> 04889349361 | N1116: =(3000000000000+M1116) -> 3004889349361 | O1116: =(5000000000000+M1116) -> 5004889349361 | P1116: {=N1116 & MOD(10 - MOD(SUMPRODUCT(MID(N1116, ROW(INDIRECT("1:" & LEN(N1116))), 1) * IF(MOD(ROW(INDIRECT("1:" & LEN(N1116))), 2) = 0, 1, 3)), 10), 10)} -> 30048893493616
A1117: 4501632 | B1117: =VLOOKUP(A1117, Sheet1!A:Z, 2, FALSE) -> 2 | C1117: 2 | D1117: {=--_xlfn.TEXTJOIN("",TRUE,IF(ISNUMBER(MID(LEFT(MID(VLOOKUP(A1117,Sheet1!A:Z,12,FALSE),2,99),FIND(")",VLOOKUP(A1117,Sheet1!A:Z,12,FALSE))-2),ROW($1:$20),1)+0),MID(LEFT(MID(VLOOKUP(A1117,Sheet1!A:Z,12,FALSE),2,99),FIND(")",VLOOKUP(A1117,Sheet1!A:Z,12,FALSE))-2),ROW($1:$20),1),""))} -> 2 | E1117: =IF(ISNUMBER(SEARCH("Minimum", VLOOKUP(A1117, Sheet1!A:Z, 12, FALSE))), TRUE, FALSE) -> FALSE | F1117: =QUOTIENT(B1117, C1117) -> 1 | G1117: =VALUE(VLOOKUP(A1117, Sheet1!A:Z, 11, FALSE))>=10 -> TRUE | H1117: =VLOOKUP(A1117, Sheet1!A:Z, 11, FALSE) -> 35.55 | I1117: =VLOOKUP(A1117, Sheet1!A:Z, 13, FALSE) -> 30.90 | J1117: =IF(E1117, I1117, IF(C1117<>D1117,I1117,H1117)) -> 30.90 | K1117: =(J1117+20%)*2.8 -> 87.08 | L1117: =VLOOKUP(A1117, Sheet1!A:Z, 5, FALSE) -> 048893447892 | M1117: =LEFT(L1117, LEN(L1117)-1) -> 04889344789 | N1117: =(3000000000000+M1117) -> 3004889344789 | O1117: =(5000000000000+M1117) -> 5004889344789 | P1117: {=N1117 & MOD(10 - MOD(SUMPRODUCT(MID(N1117, ROW(INDIRECT("1:" & LEN(N1117))), 1) * IF(MOD(ROW(INDIRECT("1:" & LEN(N1117))), 2) = 0, 1, 3)), 10), 10)} -> 30048893447893
A1118: 4510447 | B1118: =VLOOKUP(A1118, Sheet1!A:Z, 2, FALSE) -> 2 | C1118: 2 | D1118: {=--_xlfn.TEXTJOIN("",TRUE,IF(ISNUMBER(MID(LEFT(MID(VLOOKUP(A1118,Sheet1!A:Z,12,FALSE),2,99),FIND(")",VLOOKUP(A1118,Sheet1!A:Z,12,FALSE))-2),ROW($1:$20),1)+0),MID(LEFT(MID(VLOOKUP(A1118,Sheet1!A:Z,12,FALSE),2,99),FIND(")",VLOOKUP(A1118,Sheet1!A:Z,12,FALSE))-2),ROW($1:$20),1),""))} -> 2 | E1118: =IF(ISNUMBER(SEARCH("Minimum", VLOOKUP(A1118, Sheet1!A:Z, 12, FALSE))), TRUE, FALSE) -> FALSE | F1118: =QUOTIENT(B1118, C1118) -> 1 | G1118: =VALUE(VLOOKUP(A1118, Sheet1!A:Z, 11, FALSE))>=10 -> TRUE | H1118: =VLOOKUP(A1118, Sheet1!A:Z, 11, FALSE) -> 33.55 | I1118: =VLOOKUP(A1118, Sheet1!A:Z, 13, FALSE) -> 29.70 | J1118: =IF(E1118, I1118, IF(C1118<>D1118,I1118,H1118)) -> 29.70 | K1118: =(J1118+20%)*2.8 -> 83.72 | L1118: =VLOOKUP(A1118, Sheet1!A:Z, 5, FALSE) -> 048893959050 | M1118: =LEFT(L1118, LEN(L1118)-1) -> 04889395905 | N1118: =(3000000000000+M1118) -> 3004889395905 | O1118: =(5000000000000+M1118) -> 5004889395905 | P1118: {=N1118 & MOD(10 - MOD(SUMPRODUCT(MID(N1118, ROW(INDIRECT("1:" & LEN(N1118))), 1) * IF(MOD(ROW(INDIRECT("1:" & LEN(N1118))), 2) = 0, 1, 3)), 10), 10)} -> 30048893959051
A1119: 4511695 | B1119: =VLOOKUP(A1119, Sheet1!A:Z, 2, FALSE) -> 2 | C1119: 2 | D1119: {=--_xlfn.TEXTJOIN("",TRUE,IF(ISNUMBER(MID(LEFT(MID(VLOOKUP(A1119,Sheet1!A:Z,12,FALSE),2,99),FIND(")",VLOOKUP(A1119,Sheet1!A:Z,12,FALSE))-2),ROW($1:$20),1)+0),MID(LEFT(MID(VLOOKUP(A1119,Sheet1!A:Z,12,FALSE),2,99),FIND(")",VLOOKUP(A1119,Sheet1!A:Z,12,FALSE))-2),ROW($1:$20),1),""))} -> 2 | E1119: =IF(ISNUMBER(SEARCH("Minimum", VLOOKUP(A1119, Sheet1!A:Z, 12, FALSE))), TRUE, FALSE) -> FALSE | F1119: =QUOTIENT(B1119, C1119) -> 1 | G1119: =VALUE(VLOOKUP(A1119, Sheet1!A:Z, 11, FALSE))>=10 -> TRUE | H1119: =VLOOKUP(A1119, Sheet1!A:Z, 11, FALSE) -> 54.10 | I1119: =VLOOKUP(A1119, Sheet1!A:Z, 13, FALSE) -> 47.90 | J1119: =IF(E1119, I1119, IF(C1119<>D1119,I1119,H1119)) -> 47.90 | K1119: =(J1119+20%)*2.8 -> 134.68 | L1119: =VLOOKUP(A1119, Sheet1!A:Z, 5, FALSE) -> 048893444792 | M1119: =LEFT(L1119, LEN(L1119)-1) -> 04889344479 | N1119: =(3000000000000+M1119) -> 3004889344479 | O1119: =(5000000000000+M1119) -> 5004889344479 | P1119: {=N1119 & MOD(10 - MOD(SUMPRODUCT(MID(N1119, ROW(INDIRECT("1:" & LEN(N1119))), 1) * IF(MOD(ROW(INDIRECT("1:" & LEN(N1119))), 2) = 0, 1, 3)), 10), 10)} -> 30048893444793
A1120: 4511708 | B1120: =VLOOKUP(A1120, Sheet1!A:Z, 2, FALSE) -> 2 | C1120: 2 | D1120: {=--_xlfn.TEXTJOIN("",TRUE,IF(ISNUMBER(MID(LEFT(MID(VLOOKUP(A1120,Sheet1!A:Z,12,FALSE),2,99),FIND(")",VLOOKUP(A1120,Sheet1!A:Z,12,FALSE))-2),ROW($1:$20),1)+0),MID(LEFT(MID(VLOOKUP(A1120,Sheet1!A:Z,12,FALSE),2,99),FIND(")",VLOOKUP(A1120,Sheet1!A:Z,12,FALSE))-2),ROW($1:$20),1),""))} -> 2 | E1120: =IF(ISNUMBER(SEARCH("Minimum", VLOOKUP(A1120, Sheet1!A:Z, 12, FALSE))), TRUE, FALSE) -> FALSE | F1120: =QUOTIENT(B1120, C1120) -> 1 | G1120: =VALUE(VLOOKUP(A1120, Sheet1!A:Z, 11, FALSE))>=10 -> TRUE | H1120: =VLOOKUP(A1120, Sheet1!A:Z, 11, FALSE) -> 41.00 | I1120: =VLOOKUP(A1120, Sheet1!A:Z, 13, FALSE) -> 36.40 | J1120: =IF(E1120, I1120, IF(C1120<>D1120,I1120,H1120)) -> 36.40 | K1120: =(J1120+20%)*2.8 -> 102.48 | L1120: =VLOOKUP(A1120, Sheet1!A:Z, 5, FALSE) -> 048893444662 | M1120: =LEFT(L1120, LEN(L1120)-1) -> 04889344466 | N1120: =(3000000000000+M1120) -> 3004889344466 | O1120: =(5000000000000+M1120) -> 5004889344466 | P1120: {=N1120 & MOD(10 - MOD(SUMPRODUCT(MID(N1120, ROW(INDIRECT("1:" & LEN(N1120))), 1) * IF(MOD(ROW(INDIRECT("1:" & LEN(N1120))), 2) = 0, 1, 3)), 10), 10)} -> 30048893444663
A1121: 4512264 | B1121: =VLOOKUP(A1121, Sheet1!A:Z, 2, FALSE) -> 2 | C1121: 2 | D1121: {=--_xlfn.TEXTJOIN("",TRUE,IF(ISNUMBER(MID(LEFT(MID(VLOOKUP(A1121,Sheet1!A:Z,12,FALSE),2,99),FIND(")",VLOOKUP(A1121,Sheet1!A:Z,12,FALSE))-2),ROW($1:$20),1)+0),MID(LEFT(MID(VLOOKUP(A1121,Sheet1!A:Z,12,FALSE),2,99),FIND(")",VLOOKUP(A1121,Sheet1!A:Z,12,FALSE))-2),ROW($1:$20),1),""))} -> 2 | E1121: =IF(ISNUMBER(SEARCH("Minimum", VLOOKUP(A1121, Sheet1!A:Z, 12, FALSE))), TRUE, FALSE) -> FALSE | F1121: =QUOTIENT(B1121, C1121) -> 1 | G1121: =VALUE(VLOOKUP(A1121, Sheet1!A:Z, 11, FALSE))>=10 -> TRUE | H1121: =VLOOKUP(A1121, Sheet1!A:Z, 11, FALSE) -> 57.35 | I1121: =VLOOKUP(A1121, Sheet1!A:Z, 13, FALSE) -> 50.80 | J1121: =IF(E1121, I1121, IF(C1121<>D1121,I1121,H1121)) -> 50.80 | K1121: =(J1121+20%)*2.8 -> 142.8 | L1121: =VLOOKUP(A1121, Sheet1!A:Z, 5, FALSE) -> 048893443818 | M1121: =LEFT(L1121, LEN(L1121)-1) -> 04889344381 | N1121: =(3000000000000+M1121) -> 3004889344381 | O1121: =(5000000000000+M1121) -> 5004889344381 | P1121: {=N1121 & MOD(10 - MOD(SUMPRODUCT(MID(N1121, ROW(INDIRECT("1:" & LEN(N1121))), 1) * IF(MOD(ROW(INDIRECT("1:" & LEN(N1121))), 2) = 0, 1, 3)), 10), 10)} -> 30048893443819
A1122: 4515558 | B1122: =VLOOKUP(A1122, Sheet1!A:Z, 2, FALSE) -> 2 | C1122: 2 | D1122: {=--_xlfn.TEXTJOIN("",TRUE,IF(ISNUMBER(MID(LEFT(MID(VLOOKUP(A1122,Sheet1!A:Z,12,FALSE),2,99),FIND(")",VLOOKUP(A1122,Sheet1!A:Z,12,FALSE))-2),ROW($1:$20),1)+0),MID(LEFT(MID(VLOOKUP(A1122,Sheet1!A:Z,12,FALSE),2,99),FIND(")",VLOOKUP(A1122,Sheet1!A:Z,12,FALSE))-2),ROW($1:$20),1),""))} -> 2 | E1122: =IF(ISNUMBER(SEARCH("Minimum", VLOOKUP(A1122, Sheet1!A:Z, 12, FALSE))), TRUE, FALSE) -> FALSE | F1122: =QUOTIENT(B1122, C1122) -> 1 | G1122: =VALUE(VLOOKUP(A1122, Sheet1!A:Z, 11, FALSE))>=10 -> TRUE | H1122: =VLOOKUP(A1122, Sheet1!A:Z, 11, FALSE) -> 57.10 | I1122: =VLOOKUP(A1122, Sheet1!A:Z, 13, FALSE) -> 50.50 | J1122: =IF(E1122, I1122, IF(C1122<>D1122,I1122,H1122)) -> 50.50 | K1122: =(J1122+20%)*2.8 -> 141.96 | L1122: =VLOOKUP(A1122, Sheet1!A:Z, 5, FALSE) -> 048893955328 | M1122: =LEFT(L1122, LEN(L1122)-1) -> 04889395532 | N1122: =(3000000000000+M1122) -> 3004889395532 | O1122: =(5000000000000+M1122) -> 5004889395532 | P1122: {=N1122 & MOD(10 - MOD(SUMPRODUCT(MID(N1122, ROW(INDIRECT("1:" & LEN(N1122))), 1) * IF(MOD(ROW(INDIRECT("1:" & LEN(N1122))), 2) = 0, 1, 3)), 10), 10)} -> 30048893955329
A1123: 4516223 | B1123: =VLOOKUP(A1123, Sheet1!A:Z, 2, FALSE) -> 2 | C1123: 2 | D1123: {=--_xlfn.TEXTJOIN("",TRUE,IF(ISNUMBER(MID(LEFT(MID(VLOOKUP(A1123,Sheet1!A:Z,12,FALSE),2,99),FIND(")",VLOOKUP(A1123,Sheet1!A:Z,12,FALSE))-2),ROW($1:$20),1)+0),MID(LEFT(MID(VLOOKUP(A1123,Sheet1!A:Z,12,FALSE),2,99),FIND(")",VLOOKUP(A1123,Sheet1!A:Z,12,FALSE))-2),ROW($1:$20),1),""))} -> 2 | E1123: =IF(ISNUMBER(SEARCH("Minimum", VLOOKUP(A1123, Sheet1!A:Z, 12, FALSE))), TRUE, FALSE) -> FALSE | F1123: =QUOTIENT(B1123, C1123) -> 1 | G1123: =VALUE(VLOOKUP(A1123, Sheet1!A:Z, 11, FALSE))>=10 -> TRUE | H1123: =VLOOKUP(A1123, Sheet1!A:Z, 11, FALSE) -> 43.95 | I1123: =VLOOKUP(A1123, Sheet1!A:Z, 13, FALSE) -> 38.85 | J1123: =IF(E1123, I1123, IF(C1123<>D1123,I1123,H1123)) -> 38.85 | K1123: =(J1123+20%)*2.8 -> 109.34 | L1123: =VLOOKUP(A1123, Sheet1!A:Z, 5, FALSE) -> 048893442798 | M1123: =LEFT(L1123, LEN(L1123)-1) -> 04889344279 | N1123: =(3000000000000+M1123) -> 3004889344279 | O1123: =(5000000000000+M1123) -> 5004889344279 | P1123: {=N1123 & MOD(10 - MOD(SUMPRODUCT(MID(N1123, ROW(INDIRECT("1:" & LEN(N1123))), 1) * IF(MOD(ROW(INDIRECT("1:" & LEN(N1123))), 2) = 0, 1, 3)), 10), 10)} -> 30048893442799
A1124: 4522910 | B1124: =VLOOKUP(A1124, Sheet1!A:Z, 2, FALSE) -> 2 | C1124: 2 | D1124: {=--_xlfn.TEXTJOIN("",TRUE,IF(ISNUMBER(MID(LEFT(MID(VLOOKUP(A1124,Sheet1!A:Z,12,FALSE),2,99),FIND(")",VLOOKUP(A1124,Sheet1!A:Z,12,FALSE))-2),ROW($1:$20),1)+0),MID(LEFT(MID(VLOOKUP(A1124,Sheet1!A:Z,12,FALSE),2,99),FIND(")",VLOOKUP(A1124,Sheet1!A:Z,12,FALSE))-2),ROW($1:$20),1),""))} -> 2 | E1124: =IF(ISNUMBER(SEARCH("Minimum", VLOOKUP(A1124, Sheet1!A:Z, 12, FALSE))), TRUE, FALSE) -> FALSE | F1124: =QUOTIENT(B1124, C1124) -> 1 | G1124: =VALUE(VLOOKUP(A1124, Sheet1!A:Z, 11, FALSE))>=10 -> TRUE | H1124: =VLOOKUP(A1124, Sheet1!A:Z, 11, FALSE) -> 47.90 | I1124: =VLOOKUP(A1124, Sheet1!A:Z, 13, FALSE) -> 42.60 | J1124: =IF(E1124, I1124, IF(C1124<>D1124,I1124,H1124)) -> 42.60 | K1124: =(J1124+20%)*2.8 -> 119.84 | L1124: =VLOOKUP(A1124, Sheet1!A:Z, 5, FALSE) -> 048893438487 | M1124: =LEFT(L1124, LEN(L1124)-1) -> 04889343848 | N1124: =(3000000000000+M1124) -> 3004889343848 | O1124: =(5000000000000+M1124) -> 5004889343848 | P1124: {=N1124 & MOD(10 - MOD(SUMPRODUCT(MID(N1124, ROW(INDIRECT("1:" & LEN(N1124))), 1) * IF(MOD(ROW(INDIRECT("1:" & LEN(N1124))), 2) = 0, 1, 3)), 10), 10)} -> 30048893438488
... A1131: X4221017 | B1131: =VLOOKUP(A1131, Sheet1!A:Z, 2, FALSE) -> 2 | C1131: 2 | D1131: {=--_xlfn.TEXTJOIN("",TRUE,IF(ISNUMBER(MID(LEFT(MID(VLOOKUP(A1131,Sheet1!A:Z,12,FALSE),2,99),FIND(")",VLOOKUP(A1131,Sheet1!A:Z,12,FALSE))-2),ROW($1:$20),1)+0),MID(LEFT(MID(VLOOKUP(A1131,Sheet1!A:Z,12,FALSE),2,99),FIND(")",VLOOKUP(A1131,Sheet1!A:Z,12,FALSE))-2),ROW($1:$20),1),""))} -> 2 | E1131: =IF(ISNUMBER(SEARCH("Minimum", VLOOKUP(A1131, Sheet1!A:Z, 12, FALSE))), TRUE, FALSE) -> FALSE | F1131: =QUOTIENT(B1131, C1131) -> 1 | G1131: =VALUE(VLOOKUP(A1131, Sheet1!A:Z, 11, FALSE))>=10 -> TRUE | H1131: =VLOOKUP(A1131, Sheet1!A:Z, 11, FALSE) -> 70.00 | I1131: =VLOOKUP(A1131, Sheet1!A:Z, 13, FALSE) -> 62.00 | J1131: =IF(E1131, I1131, IF(C1131<>D1131,I1131,H1131)) -> 62.00 | K1131: =(J1131+20%)*2.8 -> 174.16 | L1131: =VLOOKUP(A1131, Sheet1!A:Z, 5, FALSE) -> 048893752675 | M1131: =LEFT(L1131, LEN(L1131)-1) -> 04889375267 | N1131: =(3000000000000+M1131) -> 3004889375267 | O1131: =(5000000000000+M1131) -> 5004889375267 | P1131: {=N1131 & MOD(10 - MOD(SUMPRODUCT(MID(N1131, ROW(INDIRECT("1:" & LEN(N1131))), 1) * IF(MOD(ROW(INDIRECT("1:" & LEN(N1131))), 2) = 0, 1, 3)), 10), 10)} -> 30048893752676
A1132: 4018503 | B1132: =VLOOKUP(A1132, Sheet1!A:Z, 2, FALSE) -> 1 | D1132: {=--_xlfn.TEXTJOIN("",TRUE,IF(ISNUMBER(MID(LEFT(MID(VLOOKUP(A1132,Sheet1!A:Z,12,FALSE),2,99),FIND(")",VLOOKUP(A1132,Sheet1!A:Z,12,FALSE))-2),ROW($1:$20),1)+0),MID(LEFT(MID(VLOOKUP(A1132,Sheet1!A:Z,12,FALSE),2,99),FIND(")",VLOOKUP(A1132,Sheet1!A:Z,12,FALSE))-2),ROW($1:$20),1),""))} -> 2 | E1132: =IF(ISNUMBER(SEARCH("Minimum", VLOOKUP(A1132, Sheet1!A:Z, 12, FALSE))), TRUE, FALSE) -> FALSE | F1132: =QUOTIENT(B1132, C1132) -> #DIV/0! | G1132: =VALUE(VLOOKUP(A1132, Sheet1!A:Z, 11, FALSE))>=10 -> TRUE | H1132: =VLOOKUP(A1132, Sheet1!A:Z, 11, FALSE) -> 57.20 | I1132: =VLOOKUP(A1132, Sheet1!A:Z, 13, FALSE) -> 50.90 | J1132: =IF(E1132, I1132, IF(C1132<>D1132,I1132,H1132)) -> 50.90 | K1132: =(J1132+20%)*2.8 -> 143.08 | L1132: =VLOOKUP(A1132, Sheet1!A:Z, 5, FALSE) -> 048893163150 | M1132: =LEFT(L1132, LEN(L1132)-1) -> 04889316315 | N1132: =(3000000000000+M1132) -> 3004889316315 | O1132: =(5000000000000+M1132) -> 5004889316315 | P1132: {=N1132 & MOD(10 - MOD(SUMPRODUCT(MID(N1132, ROW(INDIRECT("1:" & LEN(N1132))), 1) * IF(MOD(ROW(INDIRECT("1:" & LEN(N1132))), 2) = 0, 1, 3)), 10), 10)} -> 30048893163151
A1133: 4114106 | B1133: =VLOOKUP(A1133, Sheet1!A:Z, 2, FALSE) -> 1 | D1133: {=--_xlfn.TEXTJOIN("",TRUE,IF(ISNUMBER(MID(LEFT(MID(VLOOKUP(A1133,Sheet1!A:Z,12,FALSE),2,99),FIND(")",VLOOKUP(A1133,Sheet1!A:Z,12,FALSE))-2),ROW($1:$20),1)+0),MID(LEFT(MID(VLOOKUP(A1133,Sheet1!A:Z,12,FALSE),2,99),FIND(")",VLOOKUP(A1133,Sheet1!A:Z,12,FALSE))-2),ROW($1:$20),1),""))} -> 2 | E1133: =IF(ISNUMBER(SEARCH("Minimum", VLOOKUP(A1133, Sheet1!A:Z, 12, FALSE))), TRUE, FALSE) -> TRUE | F1133: =QUOTIENT(B1133, C1133) -> #DIV/0! | G1133: =VALUE(VLOOKUP(A1133, Sheet1!A:Z, 11, FALSE))>=10 -> TRUE | H1133: =VLOOKUP(A1133, Sheet1!A:Z, 11, FALSE) -> 42.70 | I1133: =VLOOKUP(A1133, Sheet1!A:Z, 13, FALSE) -> 22.15 | J1133: =IF(E1133, I1133, IF(C1133<>D1133,I1133,H1133)) -> 22.15 | K1133: =(J1133+20%)*2.8 -> 62.58 | L1133: =VLOOKUP(A1133, Sheet1!A:Z, 5, FALSE) -> 048893205430 | M1133: =LEFT(L1133, LEN(L1133)-1) -> 04889320543 | N1133: =(3000000000000+M1133) -> 3004889320543 | O1133: =(5000000000000+M1133) -> 5004889320543 | P1133: {=N1133 & MOD(10 - MOD(SUMPRODUCT(MID(N1133, ROW(INDIRECT("1:" & LEN(N1133))), 1) * IF(MOD(ROW(INDIRECT("1:" & LEN(N1133))), 2) = 0, 1, 3)), 10), 10)} -> 30048893205431
A1134: 4200758 | B1134: =VLOOKUP(A1134, Sheet1!A:Z, 2, FALSE) -> 1 | D1134: {=--_xlfn.TEXTJOIN("",TRUE,IF(ISNUMBER(MID(LEFT(MID(VLOOKUP(A1134,Sheet1!A:Z,12,FALSE),2,99),FIND(")",VLOOKUP(A1134,Sheet1!A:Z,12,FALSE))-2),ROW($1:$20),1)+0),MID(LEFT(MID(VLOOKUP(A1134,Sheet1!A:Z,12,FALSE),2,99),FIND(")",VLOOKUP(A1134,Sheet1!A:Z,12,FALSE))-2),ROW($1:$20),1),""))} -> 4 | E1134: =IF(ISNUMBER(SEARCH("Minimum", VLOOKUP(A1134, Sheet1!A:Z, 12, FALSE))), TRUE, FALSE) -> FALSE | F1134: =QUOTIENT(B1134, C1134) -> #DIV/0! | G1134: =VALUE(VLOOKUP(A1134, Sheet1!A:Z, 11, FALSE))>=10 -> TRUE | H1134: =VLOOKUP(A1134, Sheet1!A:Z, 11, FALSE) -> 46.00 | I1134: =VLOOKUP(A1134, Sheet1!A:Z, 13, FALSE) -> 40.45 | J1134: =IF(E1134, I1134, IF(C1134<>D1134,I1134,H1134)) -> 40.45 | K1134: =(J1134+20%)*2.8 -> 113.82 | L1134: =VLOOKUP(A1134, Sheet1!A:Z, 5, FALSE) -> 048893810405 | M1134: =LEFT(L1134, LEN(L1134)-1) -> 04889381040 | N1134: =(3000000000000+M1134) -> 3004889381040 | O1134: =(5000000000000+M1134) -> 5004889381040 | P1134: {=N1134 & MOD(10 - MOD(SUMPRODUCT(MID(N1134, ROW(INDIRECT("1:" & LEN(N1134))), 1) * IF(MOD(ROW(INDIRECT("1:" & LEN(N1134))), 2) = 0, 1, 3)), 10), 10)} -> 30048893810406
A1135: 4211199 | B1135: =VLOOKUP(A1135, Sheet1!A:Z, 2, FALSE) -> 1 | D1135: {=--_xlfn.TEXTJOIN("",TRUE,IF(ISNUMBER(MID(LEFT(MID(VLOOKUP(A1135,Sheet1!A:Z,12,FALSE),2,99),FIND(")",VLOOKUP(A1135,Sheet1!A:Z,12,FALSE))-2),ROW($1:$20),1)+0),MID(LEFT(MID(VLOOKUP(A1135,Sheet1!A:Z,12,FALSE),2,99),FIND(")",VLOOKUP(A1135,Sheet1!A:Z,12,FALSE))-2),ROW($1:$20),1),""))} -> 2 | E1135: =IF(ISNUMBER(SEARCH("Minimum", VLOOKUP(A1135, Sheet1!A:Z, 12, FALSE))), TRUE, FALSE) -> TRUE | F1135: =QUOTIENT(B1135, C1135) -> #DIV/0! | G1135: =VALUE(VLOOKUP(A1135, Sheet1!A:Z, 11, FALSE))>=10 -> TRUE | H1135: =VLOOKUP(A1135, Sheet1!A:Z, 11, FALSE) -> 48.50 | I1135: =VLOOKUP(A1135, Sheet1!A:Z, 13, FALSE) -> 25.80 | J1135: =IF(E1135, I1135, IF(C1135<>D1135,I1135,H1135)) -> 25.80 | K1135: =(J1135+20%)*2.8 -> 72.8 | L1135: =VLOOKUP(A1135, Sheet1!A:Z, 5, FALSE) -> 048893798376 | M1135: =LEFT(L1135, LEN(L1135)-1) -> 04889379837 | N1135: =(3000000000000+M1135) -> 3004889379837 | O1135: =(5000000000000+M1135) -> 5004889379837 | P1135: {=N1135 & MOD(10 - MOD(SUMPRODUCT(MID(N1135, ROW(INDIRECT("1:" & LEN(N1135))), 1) * IF(MOD(ROW(INDIRECT("1:" & LEN(N1135))), 2) = 0, 1, 3)), 10), 10)} -> 30048893798377
A1136: 4215518 | B1136: =VLOOKUP(A1136, Sheet1!A:Z, 2, FALSE) -> 1 | C1136: 1 | D1136: {=--_xlfn.TEXTJOIN("",TRUE,IF(ISNUMBER(MID(LEFT(MID(VLOOKUP(A1136,Sheet1!A:Z,12,FALSE),2,99),FIND(")",VLOOKUP(A1136,Sheet1!A:Z,12,FALSE))-2),ROW($1:$20),1)+0),MID(LEFT(MID(VLOOKUP(A1136,Sheet1!A:Z,12,FALSE),2,99),FIND(")",VLOOKUP(A1136,Sheet1!A:Z,12,FALSE))-2),ROW($1:$20),1),""))} -> 1 | E1136: =IF(ISNUMBER(SEARCH("Minimum", VLOOKUP(A1136, Sheet1!A:Z, 12, FALSE))), TRUE, FALSE) -> FALSE | F1136: =QUOTIENT(B1136, C1136) -> 1 | G1136: =VALUE(VLOOKUP(A1136, Sheet1!A:Z, 11, FALSE))>=10 -> TRUE | H1136: =VLOOKUP(A1136, Sheet1!A:Z, 11, FALSE) -> 82.00 | I1136: =VLOOKUP(A1136, Sheet1!A:Z, 13, FALSE) -> 73.50 | J1136: =IF(E1136, I1136, IF(C1136<>D1136,I1136,H1136)) -> 73.50 | K1136: =(J1136+20%)*2.8 -> 206.36 | L1136: =VLOOKUP(A1136, Sheet1!A:Z, 5, FALSE) -> 048893652081 | M1136: =LEFT(L1136, LEN(L1136)-1) -> 04889365208 | N1136: =(3000000000000+M1136) -> 3004889365208 | O1136: =(5000000000000+M1136) -> 5004889365208 | P1136: {=N1136 & MOD(10 - MOD(SUMPRODUCT(MID(N1136, ROW(INDIRECT("1:" & LEN(N1136))), 1) * IF(MOD(ROW(INDIRECT("1:" & LEN(N1136))), 2) = 0, 1, 3)), 10), 10)} -> 30048893652082
A1137: 4313507 | B1137: =VLOOKUP(A1137, Sheet1!A:Z, 2, FALSE) -> 1 | D1137: {=--_xlfn.TEXTJOIN("",TRUE,IF(ISNUMBER(MID(LEFT(MID(VLOOKUP(A1137,Sheet1!A:Z,12,FALSE),2,99),FIND(")",VLOOKUP(A1137,Sheet1!A:Z,12,FALSE))-2),ROW($1:$20),1)+0),MID(LEFT(MID(VLOOKUP(A1137,Sheet1!A:Z,12,FALSE),2,99),FIND(")",VLOOKUP(A1137,Sheet1!A:Z,12,FALSE))-2),ROW($1:$20),1),""))} -> 2 | E1137: =IF(ISNUMBER(SEARCH("Minimum", VLOOKUP(A1137, Sheet1!A:Z, 12, FALSE))), TRUE, FALSE) -> TRUE | F1137: =QUOTIENT(B1137, C1137) -> #DIV/0! | G1137: =VALUE(VLOOKUP(A1137, Sheet1!A:Z, 11, FALSE))>=10 -> TRUE | H1137: =VLOOKUP(A1137, Sheet1!A:Z, 11, FALSE) -> 76.50 | I1137: =VLOOKUP(A1137, Sheet1!A:Z, 13, FALSE) -> 41.10 | J1137: =IF(E1137, I1137, IF(C1137<>D1137,I1137,H1137)) -> 41.10 | K1137: =(J1137+20%)*2.8 -> 115.64 | L1137: =VLOOKUP(A1137, Sheet1!A:Z, 5, FALSE) -> 048893556181 | M1137: =LEFT(L1137, LEN(L1137)-1) -> 04889355618 | N1137: =(3000000000000+M1137) -> 3004889355618 | O1137: =(5000000000000+M1137) -> 5004889355618 | P1137: {=N1137 & MOD(10 - MOD(SUMPRODUCT(MID(N1137, ROW(INDIRECT("1:" & LEN(N1137))), 1) * IF(MOD(ROW(INDIRECT("1:" & LEN(N1137))), 2) = 0, 1, 3)), 10), 10)} -> 30048893556182
A1138: 4501666 | B1138: =VLOOKUP(A1138, Sheet1!A:Z, 2, FALSE) -> 1 | D1138: {=--_xlfn.TEXTJOIN("",TRUE,IF(ISNUMBER(MID(LEFT(MID(VLOOKUP(A1138,Sheet1!A:Z,12,FALSE),2,99),FIND(")",VLOOKUP(A1138,Sheet1!A:Z,12,FALSE))-2),ROW($1:$20),1)+0),MID(LEFT(MID(VLOOKUP(A1138,Sheet1!A:Z,12,FALSE),2,99),FIND(")",VLOOKUP(A1138,Sheet1!A:Z,12,FALSE))-2),ROW($1:$20),1),""))} -> 2 | E1138: =IF(ISNUMBER(SEARCH("Minimum", VLOOKUP(A1138, Sheet1!A:Z, 12, FALSE))), TRUE, FALSE) -> FALSE | F1138: =QUOTIENT(B1138, C1138) -> #DIV/0! | G1138: =VALUE(VLOOKUP(A1138, Sheet1!A:Z, 11, FALSE))>=10 -> TRUE | H1138: =VLOOKUP(A1138, Sheet1!A:Z, 11, FALSE) -> 69.20 | I1138: =VLOOKUP(A1138, Sheet1!A:Z, 13, FALSE) -> 61.75 | J1138: =IF(E1138, I1138, IF(C1138<>D1138,I1138,H1138)) -> 61.75 | K1138: =(J1138+20%)*2.8 -> 173.46 | L1138: =VLOOKUP(A1138, Sheet1!A:Z, 5, FALSE) -> 048893447762 | M1138: =LEFT(L1138, LEN(L1138)-1) -> 04889344776 | N1138: =(3000000000000+M1138) -> 3004889344776 | O1138: =(5000000000000+M1138) -> 5004889344776 | P1138: {=N1138 & MOD(10 - MOD(SUMPRODUCT(MID(N1138, ROW(INDIRECT("1:" & LEN(N1138))), 1) * IF(MOD(ROW(INDIRECT("1:" & LEN(N1138))), 2) = 0, 1, 3)), 10), 10)} -> 30048893447763
A1139: 4511644 | B1139: =VLOOKUP(A1139, Sheet1!A:Z, 2, FALSE) -> 1 | D1139: {=--_xlfn.TEXTJOIN("",TRUE,IF(ISNUMBER(MID(LEFT(MID(VLOOKUP(A1139,Sheet1!A:Z,12,FALSE),2,99),FIND(")",VLOOKUP(A1139,Sheet1!A:Z,12,FALSE))-2),ROW($1:$20),1)+0),MID(LEFT(MID(VLOOKUP(A1139,Sheet1!A:Z,12,FALSE),2,99),FIND(")",VLOOKUP(A1139,Sheet1!A:Z,12,FALSE))-2),ROW($1:$20),1),""))} -> 2 | E1139: =IF(ISNUMBER(SEARCH("Minimum", VLOOKUP(A1139, Sheet1!A:Z, 12, FALSE))), TRUE, FALSE) -> FALSE | F1139: =QUOTIENT(B1139, C1139) -> #DIV/0! | G1139: =VALUE(VLOOKUP(A1139, Sheet1!A:Z, 11, FALSE))>=10 -> TRUE | H1139: =VLOOKUP(A1139, Sheet1!A:Z, 11, FALSE) -> 54.30 | I1139: =VLOOKUP(A1139, Sheet1!A:Z, 13, FALSE) -> 47.90 | J1139: =IF(E1139, I1139, IF(C1139<>D1139,I1139,H1139)) -> 47.90 | K1139: =(J1139+20%)*2.8 -> 134.68 | L1139: =VLOOKUP(A1139, Sheet1!A:Z, 5, FALSE) -> 048893958022 | M1139: =LEFT(L1139, LEN(L1139)-1) -> 04889395802 | N1139: =(3000000000000+M1139) -> 3004889395802 | O1139: =(5000000000000+M1139) -> 5004889395802 | P1139: {=N1139 & MOD(10 - MOD(SUMPRODUCT(MID(N1139, ROW(INDIRECT("1:" & LEN(N1139))), 1) * IF(MOD(ROW(INDIRECT("1:" & LEN(N1139))), 2) = 0, 1, 3)), 10), 10)} -> 30048893958023
A1140: 4559163 | B1140: =VLOOKUP(A1140, Sheet1!A:Z, 2, FALSE) -> 1 | D1140: {=--_xlfn.TEXTJOIN("",TRUE,IF(ISNUMBER(MID(LEFT(MID(VLOOKUP(A1140,Sheet1!A:Z,12,FALSE),2,99),FIND(")",VLOOKUP(A1140,Sheet1!A:Z,12,FALSE))-2),ROW($1:$20),1)+0),MID(LEFT(MID(VLOOKUP(A1140,Sheet1!A:Z,12,FALSE),2,99),FIND(")",VLOOKUP(A1140,Sheet1!A:Z,12,FALSE))-2),ROW($1:$20),1),""))} -> 2 | E1140: =IF(ISNUMBER(SEARCH("Minimum", VLOOKUP(A1140, Sheet1!A:Z, 12, FALSE))), TRUE, FALSE) -> FALSE | F1140: =QUOTIENT(B1140, C1140) -> #DIV/0! | G1140: =VALUE(VLOOKUP(A1140, Sheet1!A:Z, 11, FALSE))>=10 -> TRUE | H1140: =VLOOKUP(A1140, Sheet1!A:Z, 11, FALSE) -> 42.40 | I1140: =VLOOKUP(A1140, Sheet1!A:Z, 13, FALSE) -> 37.50 | J1140: =IF(E1140, I1140, IF(C1140<>D1140,I1140,H1140)) -> 37.50 | K1140: =(J1140+20%)*2.8 -> 105.56 | L1140: =VLOOKUP(A1140, Sheet1!A:Z, 5, FALSE) -> 048893940577 | M1140: =LEFT(L1140, LEN(L1140)-1) -> 04889394057 | N1140: =(3000000000000+M1140) -> 3004889394057 | O1140: =(5000000000000+M1140) -> 5004889394057 | P1140: {=N1140 & MOD(10 - MOD(SUMPRODUCT(MID(N1140, ROW(INDIRECT("1:" & LEN(N1140))), 1) * IF(MOD(ROW(INDIRECT("1:" & LEN(N1140))), 2) = 0, 1, 3)), 10), 10)} -> 30048893940578
A1141: X4427911 | B1141: =VLOOKUP(A1141, Sheet1!A:Z, 2, FALSE) -> 1 | D1141: {=--_xlfn.TEXTJOIN("",TRUE,IF(ISNUMBER(MID(LEFT(MID(VLOOKUP(A1141,Sheet1!A:Z,12,FALSE),2,99),FIND(")",VLOOKUP(A1141,Sheet1!A:Z,12,FALSE))-2),ROW($1:$20),1)+0),MID(LEFT(MID(VLOOKUP(A1141,Sheet1!A:Z,12,FALSE),2,99),FIND(")",VLOOKUP(A1141,Sheet1!A:Z,12,FALSE))-2),ROW($1:$20),1),""))} -> 2 | E1141: =IF(ISNUMBER(SEARCH("Minimum", VLOOKUP(A1141, Sheet1!A:Z, 12, FALSE))), TRUE, FALSE) -> FALSE | F1141: =QUOTIENT(B1141, C1141) -> #DIV/0! | G1141: =VALUE(VLOOKUP(A1141, Sheet1!A:Z, 11, FALSE))>=10 -> TRUE | H1141: =VLOOKUP(A1141, Sheet1!A:Z, 11, FALSE) -> 143.80 | I1141: =VLOOKUP(A1141, Sheet1!A:Z, 13, FALSE) -> 143.80 | J1141: =IF(E1141, I1141, IF(C1141<>D1141,I1141,H1141)) -> 143.80 | K1141: =(J1141+20%)*2.8 -> 403.2 | L1141: =VLOOKUP(A1141, Sheet1!A:Z, 5, FALSE) -> 048893481469 | M1141: =LEFT(L1141, LEN(L1141)-1) -> 04889348146 | N1141: =(3000000000000+M1141) -> 3004889348146 | O1141: =(5000000000000+M1141) -> 5004889348146 | P1141: {=N1141 & MOD(10 - MOD(SUMPRODUCT(MID(N1141, ROW(INDIRECT("1:" & LEN(N1141))), 1) * IF(MOD(ROW(INDIRECT("1:" & LEN(N1141))), 2) = 0, 1, 3)), 10), 10)} -> 30048893481460
A1142: 2852303 | B1142: =VLOOKUP(A1142, Sheet1!A:Z, 2, FALSE) -> 0 | D1142: {=--_xlfn.TEXTJOIN("",TRUE,IF(ISNUMBER(MID(LEFT(MID(VLOOKUP(A1142,Sheet1!A:Z,12,FALSE),2,99),FIND(")",VLOOKUP(A1142,Sheet1!A:Z,12,FALSE))-2),ROW($1:$20),1)+0),MID(LEFT(MID(VLOOKUP(A1142,Sheet1!A:Z,12,FALSE),2,99),FIND(")",VLOOKUP(A1142,Sheet1!A:Z,12,FALSE))-2),ROW($1:$20),1),""))} -> 12 | E1142: =IF(ISNUMBER(SEARCH("Minimum", VLOOKUP(A1142, Sheet1!A:Z, 12, FALSE))), TRUE, FALSE) -> FALSE | F1142: =QUOTIENT(B1142, C1142) -> #DIV/0! | G1142: =VALUE(VLOOKUP(A1142, Sheet1!A:Z, 11, FALSE))>=10 -> TRUE | H1142: =VLOOKUP(A1142, Sheet1!A:Z, 11, FALSE) -> 11.70 | I1142: =VLOOKUP(A1142, Sheet1!A:Z, 13, FALSE) -> 10.20 | J1142: =IF(E1142, I1142, IF(C1142<>D1142,I1142,H1142)) -> 10.20 | K1142: =(J1142+20%)*2.8 -> 29.12 | L1142: =VLOOKUP(A1142, Sheet1!A:Z, 5, FALSE) -> 048893657215 | M1142: =LEFT(L1142, LEN(L1142)-1) -> 04889365721 | N1142: =(3000000000000+M1142) -> 3004889365721 | O1142: =(5000000000000+M1142) -> 5004889365721 | P1142: {=N1142 & MOD(10 - MOD(SUMPRODUCT(MID(N1142, ROW(INDIRECT("1:" & LEN(N1142))), 1) * IF(MOD(ROW(INDIRECT("1:" & LEN(N1142))), 2) = 0, 1, 3)), 10), 10)} -> 30048893657216
A1143: 3516162 | B1143: =VLOOKUP(A1143, Sheet1!A:Z, 2, FALSE) -> 0 | D1143: {=--_xlfn.TEXTJOIN("",TRUE,IF(ISNUMBER(MID(LEFT(MID(VLOOKUP(A1143,Sheet1!A:Z,12,FALSE),2,99),FIND(")",VLOOKUP(A1143,Sheet1!A:Z,12,FALSE))-2),ROW($1:$20),1)+0),MID(LEFT(MID(VLOOKUP(A1143,Sheet1!A:Z,12,FALSE),2,99),FIND(")",VLOOKUP(A1143,Sheet1!A:Z,12,FALSE))-2),ROW($1:$20),1),""))} -> 2 | E1143: =IF(ISNUMBER(SEARCH("Minimum", VLOOKUP(A1143, Sheet1!A:Z, 12, FALSE))), TRUE, FALSE) -> FALSE | F1143: =QUOTIENT(B1143, C1143) -> #DIV/0! | G1143: =VALUE(VLOOKUP(A1143, Sheet1!A:Z, 11, FALSE))>=10 -> TRUE | H1143: =VLOOKUP(A1143, Sheet1!A:Z, 11, FALSE) -> 53.25 | I1143: =VLOOKUP(A1143, Sheet1!A:Z, 13, FALSE) -> 47.90 | J1143: =IF(E1143, I1143, IF(C1143<>D1143,I1143,H1143)) -> 47.90 | K1143: =(J1143+20%)*2.8 -> 134.68 | L1143: =VLOOKUP(A1143, Sheet1!A:Z, 5, FALSE) -> 048893656805 | M1143: =LEFT(L1143, LEN(L1143)-1) -> 04889365680 | N1143: =(3000000000000+M1143) -> 3004889365680 | O1143: =(5000000000000+M1143) -> 5004889365680 | P1143: {=N1143 & MOD(10 - MOD(SUMPRODUCT(MID(N1143, ROW(INDIRECT("1:" & LEN(N1143))), 1) * IF(MOD(ROW(INDIRECT("1:" & LEN(N1143))), 2) = 0, 1, 3)), 10), 10)} -> 30048893656806
A1144: 3700784 | B1144: =VLOOKUP(A1144, Sheet1!A:Z, 2, FALSE) -> 0 | D1144: {=--_xlfn.TEXTJOIN("",TRUE,IF(ISNUMBER(MID(LEFT(MID(VLOOKUP(A1144,Sheet1!A:Z,12,FALSE),2,99),FIND(")",VLOOKUP(A1144,Sheet1!A:Z,12,FALSE))-2),ROW($1:$20),1)+0),MID(LEFT(MID(VLOOKUP(A1144,Sheet1!A:Z,12,FALSE),2,99),FIND(")",VLOOKUP(A1144,Sheet1!A:Z,12,FALSE))-2),ROW($1:$20),1),""))} -> 4 | E1144: =IF(ISNUMBER(SEARCH("Minimum", VLOOKUP(A1144, Sheet1!A:Z, 12, FALSE))), TRUE, FALSE) -> FALSE | F1144: =QUOTIENT(B1144, C1144) -> #DIV/0! | G1144: =VALUE(VLOOKUP(A1144, Sheet1!A:Z, 11, FALSE))>=10 -> TRUE | H1144: =VLOOKUP(A1144, Sheet1!A:Z, 11, FALSE) -> 18.10 | I1144: =VLOOKUP(A1144, Sheet1!A:Z, 13, FALSE) -> 16.00 | J1144: =IF(E1144, I1144, IF(C1144<>D1144,I1144,H1144)) -> 16.00 | K1144: =(J1144+20%)*2.8 -> 45.36 | L1144: =VLOOKUP(A1144, Sheet1!A:Z, 5, FALSE) -> 048893008741 | M1144: =LEFT(L1144, LEN(L1144)-1) -> 04889300874 | N1144: =(3000000000000+M1144) -> 3004889300874 | O1144: =(5000000000000+M1144) -> 5004889300874 | P1144: {=N1144 & MOD(10 - MOD(SUMPRODUCT(MID(N1144, ROW(INDIRECT("1:" & LEN(N1144))), 1) * IF(MOD(ROW(INDIRECT("1:" & LEN(N1144))), 2) = 0, 1, 3)), 10), 10)} -> 30048893008742
A1145: 3610334 | B1145: =VLOOKUP(A1145, Sheet1!A:Z, 2, FALSE) -> 0 | D1145: {=--_xlfn.TEXTJOIN("",TRUE,IF(ISNUMBER(MID(LEFT(MID(VLOOKUP(A1145,Sheet1!A:Z,12,FALSE),2,99),FIND(")",VLOOKUP(A1145,Sheet1!A:Z,12,FALSE))-2),ROW($1:$20),1)+0),MID(LEFT(MID(VLOOKUP(A1145,Sheet1!A:Z,12,FALSE),2,99),FIND(")",VLOOKUP(A1145,Sheet1!A:Z,12,FALSE))-2),ROW($1:$20),1),""))} -> 3 | E1145: =IF(ISNUMBER(SEARCH("Minimum", VLOOKUP(A1145, Sheet1!A:Z, 12, FALSE))), TRUE, FALSE) -> TRUE | F1145: =QUOTIENT(B1145, C1145) -> #DIV/0! | G1145: =VALUE(VLOOKUP(A1145, Sheet1!A:Z, 11, FALSE))>=10 -> TRUE | H1145: =VLOOKUP(A1145, Sheet1!A:Z, 11, FALSE) -> 24.45 | I1145: =VLOOKUP(A1145, Sheet1!A:Z, 13, FALSE) -> 12.75 | J1145: =IF(E1145, I1145, IF(C1145<>D1145,I1145,H1145)) -> 12.75 | K1145: =(J1145+20%)*2.8 -> 36.26 | L1145: =VLOOKUP(A1145, Sheet1!A:Z, 5, FALSE) -> 048893484446 | M1145: =LEFT(L1145, LEN(L1145)-1) -> 04889348444 | N1145: =(3000000000000+M1145) -> 3004889348444 | O1145: =(5000000000000+M1145) -> 5004889348444 | P1145: {=N1145 & MOD(10 - MOD(SUMPRODUCT(MID(N1145, ROW(INDIRECT("1:" & LEN(N1145))), 1) * IF(MOD(ROW(INDIRECT("1:" & LEN(N1145))), 2) = 0, 1, 3)), 10), 10)} -> 30048893484447
A1146: 3507003 | B1146: =VLOOKUP(A1146, Sheet1!A:Z, 2, FALSE) -> 0 | D1146: {=--_xlfn.TEXTJOIN("",TRUE,IF(ISNUMBER(MID(LEFT(MID(VLOOKUP(A1146,Sheet1!A:Z,12,FALSE),2,99),FIND(")",VLOOKUP(A1146,Sheet1!A:Z,12,FALSE))-2),ROW($1:$20),1)+0),MID(LEFT(MID(VLOOKUP(A1146,Sheet1!A:Z,12,FALSE),2,99),FIND(")",VLOOKUP(A1146,Sheet1!A:Z,12,FALSE))-2),ROW($1:$20),1),""))} -> 6 | E1146: =IF(ISNUMBER(SEARCH("Minimum", VLOOKUP(A1146, Sheet1!A:Z, 12, FALSE))), TRUE, FALSE) -> FALSE | F1146: =QUOTIENT(B1146, C1146) -> #DIV/0! | G1146: =VALUE(VLOOKUP(A1146, Sheet1!A:Z, 11, FALSE))>=10 -> FALSE | H1146: =VLOOKUP(A1146, Sheet1!A:Z, 11, FALSE) -> 9.95 | I1146: =VLOOKUP(A1146, Sheet1!A:Z, 13, FALSE) -> 8.50 | J1146: =IF(E1146, I1146, IF(C1146<>D1146,I1146,H1146)) -> 8.50 | K1146: =(J1146+20%)*2.8 -> 24.36 | L1146: =VLOOKUP(A1146, Sheet1!A:Z, 5, FALSE) -> 048893648022 | M1146: =LEFT(L1146, LEN(L1146)-1) -> 04889364802 | N1146: =(3000000000000+M1146) -> 3004889364802 | O1146: =(5000000000000+M1146) -> 5004889364802 | P1146: {=N1146 & MOD(10 - MOD(SUMPRODUCT(MID(N1146, ROW(INDIRECT("1:" & LEN(N1146))), 1) * IF(MOD(ROW(INDIRECT("1:" & LEN(N1146))), 2) = 0, 1, 3)), 10), 10)} -> 30048893648023
A1147: 3671351 | B1147: =VLOOKUP(A1147, Sheet1!A:Z, 2, FALSE) -> 0 | D1147: {=--_xlfn.TEXTJOIN("",TRUE,IF(ISNUMBER(MID(LEFT(MID(VLOOKUP(A1147,Sheet1!A:Z,12,FALSE),2,99),FIND(")",VLOOKUP(A1147,Sheet1!A:Z,12,FALSE))-2),ROW($1:$20),1)+0),MID(LEFT(MID(VLOOKUP(A1147,Sheet1!A:Z,12,FALSE),2,99),FIND(")",VLOOKUP(A1147,Sheet1!A:Z,12,FALSE))-2),ROW($1:$20),1),""))} -> 4 | E1147: =IF(ISNUMBER(SEARCH("Minimum", VLOOKUP(A1147, Sheet1!A:Z, 12, FALSE))), TRUE, FALSE) -> FALSE | F1147: =QUOTIENT(B1147, C1147) -> #DIV/0! | G1147: =VALUE(VLOOKUP(A1147, Sheet1!A:Z, 11, FALSE))>=10 -> TRUE | H1147: =VLOOKUP(A1147, Sheet1!A:Z, 11, FALSE) -> 17.55 | I1147: =VLOOKUP(A1147, Sheet1!A:Z, 13, FALSE) -> 15.45 | J1147: =IF(E1147, I1147, IF(C1147<>D1147,I1147,H1147)) -> 15.45 | K1147: =(J1147+20%)*2.8 -> 43.82 | L1147: =VLOOKUP(A1147, Sheet1!A:Z, 5, FALSE) -> 048893477158 | M1147: =LEFT(L1147, LEN(L1147)-1) -> 04889347715 | N1147: =(3000000000000+M1147) -> 3004889347715 | O1147: =(5000000000000+M1147) -> 5004889347715 | P1147: {=N1147 & MOD(10 - MOD(SUMPRODUCT(MID(N1147, ROW(INDIRECT("1:" & LEN(N1147))), 1) * IF(MOD(ROW(INDIRECT("1:" & LEN(N1147))), 2) = 0, 1, 3)), 10), 10)} -> 30048893477159
A1148: 17775 | B1148: =VLOOKUP(A1148, Sheet1!A:Z, 2, FALSE) -> 0 | D1148: {=--_xlfn.TEXTJOIN("",TRUE,IF(ISNUMBER(MID(LEFT(MID(VLOOKUP(A1148,Sheet1!A:Z,12,FALSE),2,99),FIND(")",VLOOKUP(A1148,Sheet1!A:Z,12,FALSE))-2),ROW($1:$20),1)+0),MID(LEFT(MID(VLOOKUP(A1148,Sheet1!A:Z,12,FALSE),2,99),FIND(")",VLOOKUP(A1148,Sheet1!A:Z,12,FALSE))-2),ROW($1:$20),1),""))} -> 4 | E1148: =IF(ISNUMBER(SEARCH("Minimum", VLOOKUP(A1148, Sheet1!A:Z, 12, FALSE))), TRUE, FALSE) -> TRUE | F1148: =QUOTIENT(B1148, C1148) -> #DIV/0! | G1148: =VALUE(VLOOKUP(A1148, Sheet1!A:Z, 11, FALSE))>=10 -> TRUE | H1148: =VLOOKUP(A1148, Sheet1!A:Z, 11, FALSE) -> 43.00 | I1148: =VLOOKUP(A1148, Sheet1!A:Z, 13, FALSE) -> 24.00 | J1148: =IF(E1148, I1148, IF(C1148<>D1148,I1148,H1148)) -> 24.00 | K1148: =(J1148+20%)*2.8 -> 67.76 | L1148: =VLOOKUP(A1148, Sheet1!A:Z, 5, FALSE) -> 048893032593 | M1148: =LEFT(L1148, LEN(L1148)-1) -> 04889303259 | N1148: =(3000000000000+M1148) -> 3004889303259 | O1148: =(5000000000000+M1148) -> 5004889303259 | P1148: {=N1148 & MOD(10 - MOD(SUMPRODUCT(MID(N1148, ROW(INDIRECT("1:" & LEN(N1148))), 1) * IF(MOD(ROW(INDIRECT("1:" & LEN(N1148))), 2) = 0, 1, 3)), 10), 10)} -> 30048893032594
... A1745: XF4522603 | B1745: =VLOOKUP(A1745, Sheet1!A:Z, 2, FALSE) -> 0 | D1745: {=--_xlfn.TEXTJOIN("",TRUE,IF(ISNUMBER(MID(LEFT(MID(VLOOKUP(A1745,Sheet1!A:Z,12,FALSE),2,99),FIND(")",VLOOKUP(A1745,Sheet1!A:Z,12,FALSE))-2),ROW($1:$20),1)+0),MID(LEFT(MID(VLOOKUP(A1745,Sheet1!A:Z,12,FALSE),2,99),FIND(")",VLOOKUP(A1745,Sheet1!A:Z,12,FALSE))-2),ROW($1:$20),1),""))} -> 12 | E1745: =IF(ISNUMBER(SEARCH("Minimum", VLOOKUP(A1745, Sheet1!A:Z, 12, FALSE))), TRUE, FALSE) -> FALSE | F1745: =QUOTIENT(B1745, C1745) -> #DIV/0! | G1745: =VALUE(VLOOKUP(A1745, Sheet1!A:Z, 11, FALSE))>=10 -> FALSE | H1745: =VLOOKUP(A1745, Sheet1!A:Z, 11, FALSE) -> 9.60 | I1745: =VLOOKUP(A1745, Sheet1!A:Z, 13, FALSE) -> 8.50 | J1745: =IF(E1745, I1745, IF(C1745<>D1745,I1745,H1745)) -> 8.50 | K1745: =(J1745+20%)*2.8 -> 24.36 | L1745: =VLOOKUP(A1745, Sheet1!A:Z, 5, FALSE) -> 048893933135 | M1745: =LEFT(L1745, LEN(L1745)-1) -> 04889393313 | N1745: =(3000000000000+M1745) -> 3004889393313 | O1745: =(5000000000000+M1745) -> 5004889393313 | P1745: {=N1745 & MOD(10 - MOD(SUMPRODUCT(MID(N1745, ROW(INDIRECT("1:" & LEN(N1745))), 1) * IF(MOD(ROW(INDIRECT("1:" & LEN(N1745))), 2) = 0, 1, 3)), 10), 10)} -> 30048893933136
A1746: 4550829 | D1746: {=--_xlfn.TEXTJOIN("",TRUE,IF(ISNUMBER(MID(LEFT(MID(VLOOKUP(A1746,Sheet1!A:Z,12,FALSE),2,99),FIND(")",VLOOKUP(A1746,Sheet1!A:Z,12,FALSE))-2),ROW($1:$20),1)+0),MID(LEFT(MID(VLOOKUP(A1746,Sheet1!A:Z,12,FALSE),2,99),FIND(")",VLOOKUP(A1746,Sheet1!A:Z,12,FALSE))-2),ROW($1:$20),1),""))} -> #VALUE! | E1746: =IF(ISNUMBER(SEARCH("Minimum", VLOOKUP(A1746, Sheet1!A:Z, 12, FALSE))), TRUE, FALSE) -> FALSE | F1746: =QUOTIENT(B1746, C1746) -> #DIV/0! | G1746: =VALUE(VLOOKUP(A1746, Sheet1!A:Z, 11, FALSE))>=10 -> FALSE | H1746: =VLOOKUP(A1746, Sheet1!A:Z, 11, FALSE) -> 0 | I1746: =VLOOKUP(A1746, Sheet1!A:Z, 13, FALSE) -> 0 | J1746: =IF(E1746, I1746, IF(C1746<>D1746,I1746,H1746)) -> #VALUE! | K1746: =(J1746+20%)*2.8 -> #VALUE! | L1746: =VLOOKUP(A1746, Sheet1!A:Z, 5, FALSE) -> 0 | M1746: =LEFT(L1746, LEN(L1746)-1) | N1746: =(3000000000000+M1746) -> #VALUE! | O1746: =(5000000000000+M1746) -> #VALUE! | P1746: {=N1746 & MOD(10 - MOD(SUMPRODUCT(MID(N1746, ROW(INDIRECT("1:" & LEN(N1746))), 1) * IF(MOD(ROW(INDIRECT("1:" & LEN(N1746))), 2) = 0, 1, 3)), 10), 10)} -> #VALUE!
A1747: F4406696 | D1747: {=--_xlfn.TEXTJOIN("",TRUE,IF(ISNUMBER(MID(LEFT(MID(VLOOKUP(A1747,Sheet1!A:Z,12,FALSE),2,99),FIND(")",VLOOKUP(A1747,Sheet1!A:Z,12,FALSE))-2),ROW($1:$20),1)+0),MID(LEFT(MID(VLOOKUP(A1747,Sheet1!A:Z,12,FALSE),2,99),FIND(")",VLOOKUP(A1747,Sheet1!A:Z,12,FALSE))-2),ROW($1:$20),1),""))} -> #VALUE! | E1747: =IF(ISNUMBER(SEARCH("Minimum", VLOOKUP(A1747, Sheet1!A:Z, 12, FALSE))), TRUE, FALSE) -> FALSE | F1747: =QUOTIENT(B1747, C1747) -> #DIV/0! | G1747: =VALUE(VLOOKUP(A1747, Sheet1!A:Z, 11, FALSE))>=10 -> FALSE | H1747: =VLOOKUP(A1747, Sheet1!A:Z, 11, FALSE) -> 0 | I1747: =VLOOKUP(A1747, Sheet1!A:Z, 13, FALSE) -> 0 | J1747: =IF(E1747, I1747, IF(C1747<>D1747,I1747,H1747)) -> #VALUE! | K1747: =(J1747+20%)*2.8 -> #VALUE! | L1747: =VLOOKUP(A1747, Sheet1!A:Z, 5, FALSE) -> 0 | M1747: =LEFT(L1747, LEN(L1747)-1) | N1747: =(3000000000000+M1747) -> #VALUE! | O1747: =(5000000000000+M1747) -> #VALUE! | P1747: {=N1747 & MOD(10 - MOD(SUMPRODUCT(MID(N1747, ROW(INDIRECT("1:" & LEN(N1747))), 1) * IF(MOD(ROW(INDIRECT("1:" & LEN(N1747))), 2) = 0, 1, 3)), 10), 10)} -> #VALUE!
